<?xml version="1.0" encoding="utf-8"?>
<!--
!!!DO NOT EDIT. THIS FILE IS GENERATED BY CODE AND ANY CHANGES MAY BE OVERWRITTEN!!!
-->
<rdf:RDF xmlns:rdf="http://www.w3.org/1999/02/22-rdf-syntax-ns#" xmlns:kc="http://knowledge.microsoft.com/configuration/" xmlns:mso="http://knowledge.microsoft.com/mso/">
  <rdf:Description rdf:about="http://knowledge.microsoft.com/mso/skiing">
    <mso:type.domain.domain_group rdf:resource="http://knowledge.microsoft.com/domain_group/sports" />
    <mso:type.object.name xml:lang="en">Skiiing</mso:type.object.name>
    <mso:type.object.type rdf:resource="http://knowledge.microsoft.com/mso/type.domain" />
  </rdf:Description>
  <rdf:Description rdf:about="http://knowledge.microsoft.com/mso/skiing.lift_tenure">
    <mso:type.object.description xml:lang="en">Relationship collecting the data for a given mso:skiing.ski_lift. Type, manufacturer, capacity, and dated of building and removal are included in this relationship.</mso:type.object.description>
    <mso:type.object.name xml:lang="en">Lift tenure</mso:type.object.name>
    <mso:type.object.type rdf:resource="http://knowledge.microsoft.com/mso/type.type" />
    <mso:type.type.category rdf:resource="http://knowledge.microsoft.com/mso/type.category.relationship" />
    <mso:type.type.domain rdf:resource="http://knowledge.microsoft.com/mso/skiing" />
    <mso:type.type.includes rdf:resource="http://knowledge.microsoft.com/mso/type.object" />
  </rdf:Description>
  <rdf:Description rdf:about="http://knowledge.microsoft.com/mso/skiing.lift_tenure.capacity">
    <mso:type.object.description xml:lang="en">The lift's capacity (per carrier, not total) during this period.</mso:type.object.description>
    <mso:type.object.name xml:lang="en">Capacity</mso:type.object.name>
    <mso:type.object.type rdf:resource="http://knowledge.microsoft.com/mso/type.property" />
    <mso:type.property.expected_type rdf:resource="http://knowledge.microsoft.com/mso/type.decimal" />
    <mso:type.property.max_cardinality rdf:datatype="http://www.w3.org/2001/XMLSchema#int">1</mso:type.property.max_cardinality>
    <mso:type.property.type rdf:resource="http://knowledge.microsoft.com/mso/skiing.lift_tenure" />
  </rdf:Description>
  <rdf:Description rdf:about="http://knowledge.microsoft.com/mso/skiing.lift_tenure.date_built">
    <mso:type.object.description xml:lang="en">The date this lift was built.</mso:type.object.description>
    <mso:type.object.name xml:lang="en">Date built</mso:type.object.name>
    <mso:type.object.type rdf:resource="http://knowledge.microsoft.com/mso/type.property" />
    <mso:type.property.expected_type rdf:resource="http://knowledge.microsoft.com/mso/type.datetime" />
    <mso:type.property.max_cardinality rdf:datatype="http://www.w3.org/2001/XMLSchema#int">1</mso:type.property.max_cardinality>
    <mso:type.property.type rdf:resource="http://knowledge.microsoft.com/mso/skiing.lift_tenure" />
  </rdf:Description>
  <rdf:Description rdf:about="http://knowledge.microsoft.com/mso/skiing.lift_tenure.date_removed">
    <mso:type.object.description xml:lang="en">The date this lift was removed or destroyed.</mso:type.object.description>
    <mso:type.object.name xml:lang="en">Date removed</mso:type.object.name>
    <mso:type.object.type rdf:resource="http://knowledge.microsoft.com/mso/type.property" />
    <mso:type.property.expected_type rdf:resource="http://knowledge.microsoft.com/mso/type.datetime" />
    <mso:type.property.max_cardinality rdf:datatype="http://www.w3.org/2001/XMLSchema#int">1</mso:type.property.max_cardinality>
    <mso:type.property.type rdf:resource="http://knowledge.microsoft.com/mso/skiing.lift_tenure" />
  </rdf:Description>
  <rdf:Description rdf:about="http://knowledge.microsoft.com/mso/skiing.lift_tenure.lift_type">
    <mso:type.object.description xml:lang="en">The type of lift used during this period.</mso:type.object.description>
    <mso:type.object.name xml:lang="en">Lift type</mso:type.object.name>
    <mso:type.object.type rdf:resource="http://knowledge.microsoft.com/mso/type.property" />
    <mso:type.property.expected_type rdf:resource="http://knowledge.microsoft.com/mso/skiing.lift_type" />
    <mso:type.property.max_cardinality rdf:datatype="http://www.w3.org/2001/XMLSchema#int">1</mso:type.property.max_cardinality>
    <mso:type.property.type rdf:resource="http://knowledge.microsoft.com/mso/skiing.lift_tenure" />
  </rdf:Description>
  <rdf:Description rdf:about="http://knowledge.microsoft.com/mso/skiing.lift_tenure.manufacturer">
    <mso:type.object.description xml:lang="en">The company that manufactured this lift.</mso:type.object.description>
    <mso:type.object.name xml:lang="en">Manufacturer</mso:type.object.name>
    <mso:type.object.type rdf:resource="http://knowledge.microsoft.com/mso/type.property" />
    <mso:type.property.expected_type rdf:resource="http://knowledge.microsoft.com/mso/skiing.ski_lift_manufacturer" />
    <mso:type.property.max_cardinality rdf:datatype="http://www.w3.org/2001/XMLSchema#int">1</mso:type.property.max_cardinality>
    <mso:type.property.type rdf:resource="http://knowledge.microsoft.com/mso/skiing.lift_tenure" />
  </rdf:Description>
  <rdf:Description rdf:about="http://knowledge.microsoft.com/mso/skiing.lift_type">
    <mso:type.object.description xml:lang="en">Primary entity representing the collection of types of ski lift. Ski lifts are the cabled devices that carry skiers up a hill. The three major types of lifts are aerial lifts, surface lifts, and cable railways.</mso:type.object.description>
    <mso:type.object.name xml:lang="en">Lift type</mso:type.object.name>
    <mso:type.object.type rdf:resource="http://knowledge.microsoft.com/mso/type.type" />
    <mso:type.type.category rdf:resource="http://knowledge.microsoft.com/mso/type.category.primary_entity" />
    <mso:type.type.domain rdf:resource="http://knowledge.microsoft.com/mso/skiing" />
    <mso:type.type.includes rdf:resource="http://knowledge.microsoft.com/mso/type.object" />
  </rdf:Description>
  <rdf:Description rdf:about="http://knowledge.microsoft.com/mso/skiing.lift_type_breakdown">
    <mso:type.object.description xml:lang="en">Relationship type collecting the data on an mso:skiing.ski_area's mso:skiing.ski_lifts. This includes the type and number of those types in this area.</mso:type.object.description>
    <mso:type.object.name xml:lang="en">Lift Type Breakdown</mso:type.object.name>
    <mso:type.object.type rdf:resource="http://knowledge.microsoft.com/mso/type.type" />
    <mso:type.type.category rdf:resource="http://knowledge.microsoft.com/mso/type.category.relationship" />
    <mso:type.type.domain rdf:resource="http://knowledge.microsoft.com/mso/skiing" />
    <mso:type.type.includes rdf:resource="http://knowledge.microsoft.com/mso/type.object" />
  </rdf:Description>
  <rdf:Description rdf:about="http://knowledge.microsoft.com/mso/skiing.lift_type_breakdown.lift_type">
    <mso:type.object.description xml:lang="en">Property relating an mso:skiing.lift_type_breakdown to an mso:skiing.lift_type found in the area.</mso:type.object.description>
    <mso:type.object.name xml:lang="en">Lift Type</mso:type.object.name>
    <mso:type.object.type rdf:resource="http://knowledge.microsoft.com/mso/type.property" />
    <mso:type.property.expected_type rdf:resource="http://knowledge.microsoft.com/mso/skiing.lift_type" />
    <mso:type.property.max_cardinality rdf:datatype="http://www.w3.org/2001/XMLSchema#int">1</mso:type.property.max_cardinality>
    <mso:type.property.type rdf:resource="http://knowledge.microsoft.com/mso/skiing.lift_type_breakdown" />
  </rdf:Description>
  <rdf:Description rdf:about="http://knowledge.microsoft.com/mso/skiing.lift_type_breakdown.number">
    <mso:type.object.description xml:lang="en">Property relating an mso:skiing.lift_type_breakdown to the number of a given mso:skiing.lift_type.</mso:type.object.description>
    <mso:type.object.name xml:lang="en">Number</mso:type.object.name>
    <mso:type.object.type rdf:resource="http://knowledge.microsoft.com/mso/type.property" />
    <mso:type.property.expected_type rdf:resource="http://knowledge.microsoft.com/mso/type.decimal" />
    <mso:type.property.max_cardinality rdf:datatype="http://www.w3.org/2001/XMLSchema#int">1</mso:type.property.max_cardinality>
    <mso:type.property.type rdf:resource="http://knowledge.microsoft.com/mso/skiing.lift_type_breakdown" />
  </rdf:Description>
  <rdf:Description rdf:about="http://knowledge.microsoft.com/mso/skiing.run_rating">
    <mso:type.object.description xml:lang="en">Enumeration type representing the kinds of ski run ratings used to describe the difficulty of a given mso:skiing.ski_run, like beginner, expert, and intermediate.</mso:type.object.description>
    <mso:type.object.name xml:lang="en">Run rating</mso:type.object.name>
    <mso:type.object.type rdf:resource="http://knowledge.microsoft.com/mso/type.type" />
    <mso:type.type.category rdf:resource="http://knowledge.microsoft.com/mso/type.category.primary_entity" />
    <mso:type.type.domain rdf:resource="http://knowledge.microsoft.com/mso/skiing" />
    <mso:type.type.includes rdf:resource="http://knowledge.microsoft.com/mso/type.object" />
  </rdf:Description>
  <rdf:Description rdf:about="http://knowledge.microsoft.com/mso/skiing.run_rating.symbol">
    <mso:type.object.description xml:lang="en">Symbol displayed visually at the ski run site and in literature and maps to indicate rating of difficulty.</mso:type.object.description>
    <mso:type.object.name xml:lang="en">Symbol</mso:type.object.name>
    <mso:type.object.type rdf:resource="http://knowledge.microsoft.com/mso/type.property" />
    <mso:type.property.expected_type rdf:resource="http://knowledge.microsoft.com/mso/skiing.run_rating_symbol" />
    <mso:type.property.max_cardinality rdf:datatype="http://www.w3.org/2001/XMLSchema#int">1</mso:type.property.max_cardinality>
    <mso:type.property.type rdf:resource="http://knowledge.microsoft.com/mso/skiing.run_rating" />
  </rdf:Description>
  <rdf:Description rdf:about="http://knowledge.microsoft.com/mso/skiing.run_rating_symbol">
    <mso:type.object.description xml:lang="en">Primary entity representing the collection of all ski run rating symbols.</mso:type.object.description>
    <mso:type.object.name xml:lang="en">Run rating symbol</mso:type.object.name>
    <mso:type.object.type rdf:resource="http://knowledge.microsoft.com/mso/type.type" />
    <mso:type.type.category rdf:resource="http://knowledge.microsoft.com/mso/type.category.primary_entity" />
    <mso:type.type.domain rdf:resource="http://knowledge.microsoft.com/mso/skiing" />
    <mso:type.type.includes rdf:resource="http://knowledge.microsoft.com/mso/type.object" />
  </rdf:Description>
  <rdf:Description rdf:about="http://knowledge.microsoft.com/mso/skiing.ski_area">
    <mso:type.object.description xml:lang="en">Primary entity representing the collection of all ski areas. Ski areas are the mountainous areas where there are ski trails and supporting services such as hotels, restaurants, and ski lifts.</mso:type.object.description>
    <mso:type.object.name xml:lang="en">Ski Area</mso:type.object.name>
    <mso:type.object.type rdf:resource="http://knowledge.microsoft.com/mso/type.type" />
    <mso:type.type.category rdf:resource="http://knowledge.microsoft.com/mso/type.category.primary_entity" />
    <mso:type.type.domain rdf:resource="http://knowledge.microsoft.com/mso/skiing" />
    <mso:type.type.includes rdf:resource="http://knowledge.microsoft.com/mso/local.entity" />
    <mso:type.type.includes rdf:resource="http://knowledge.microsoft.com/mso/location.location" />
    <mso:type.type.includes rdf:resource="http://knowledge.microsoft.com/mso/media_common.cataloged_instance" />
    <mso:type.type.includes rdf:resource="http://knowledge.microsoft.com/mso/ratings.rated_entity" />
    <mso:type.type.includes rdf:resource="http://knowledge.microsoft.com/mso/travel.destination" />
    <mso:type.type.includes rdf:resource="http://knowledge.microsoft.com/mso/type.object" />
  </rdf:Description>
  <rdf:Description rdf:about="http://knowledge.microsoft.com/mso/skiing.ski_area.base_elevation">
    <mso:type.object.description xml:lang="en">Lowest elevation of the skiable area (in meters).</mso:type.object.description>
    <mso:type.object.name xml:lang="en">Base elevation</mso:type.object.name>
    <mso:type.object.type rdf:resource="http://knowledge.microsoft.com/mso/type.property" />
    <mso:type.property.expected_type rdf:resource="http://knowledge.microsoft.com/mso/type.decimal" />
    <mso:type.property.max_cardinality rdf:datatype="http://www.w3.org/2001/XMLSchema#int">1</mso:type.property.max_cardinality>
    <mso:type.property.type rdf:resource="http://knowledge.microsoft.com/mso/skiing.ski_area" />
    <mso:type.property.unit rdf:resource="http://knowledge.microsoft.com/mso/type.unit.meter" />
  </rdf:Description>
  <rdf:Description rdf:about="http://knowledge.microsoft.com/mso/skiing.ski_area.closest_city">
    <mso:type.object.description xml:lang="en">The closest city to this ski area.</mso:type.object.description>
    <mso:type.object.name xml:lang="en">Closest city</mso:type.object.name>
    <mso:type.object.type rdf:resource="http://knowledge.microsoft.com/mso/type.property" />
    <mso:type.property.expected_type rdf:resource="http://knowledge.microsoft.com/mso/location.populated_place" />
    <mso:type.property.max_cardinality rdf:datatype="http://www.w3.org/2001/XMLSchema#int">1</mso:type.property.max_cardinality>
    <mso:type.property.type rdf:resource="http://knowledge.microsoft.com/mso/skiing.ski_area" />
  </rdf:Description>
  <rdf:Description rdf:about="http://knowledge.microsoft.com/mso/skiing.ski_area.closing_date">
    <mso:type.object.description xml:lang="en">If this ski area is no longer active, the date it closed.</mso:type.object.description>
    <mso:type.object.name xml:lang="en">Closing Date</mso:type.object.name>
    <mso:type.object.type rdf:resource="http://knowledge.microsoft.com/mso/type.property" />
    <mso:type.property.expected_type rdf:resource="http://knowledge.microsoft.com/mso/type.datetime" />
    <mso:type.property.max_cardinality rdf:datatype="http://www.w3.org/2001/XMLSchema#int">1</mso:type.property.max_cardinality>
    <mso:type.property.type rdf:resource="http://knowledge.microsoft.com/mso/skiing.ski_area" />
  </rdf:Description>
  <rdf:Description rdf:about="http://knowledge.microsoft.com/mso/skiing.ski_area.lift_type_breakdown">
    <mso:type.object.description xml:lang="en">Property relating an mso:skiing.ski_area to the mso:skiing.lift_type_breakdown, the relationship containing data for the different types and numbers of mso:skiing.ski_lifts in the area.</mso:type.object.description>
    <mso:type.object.name xml:lang="en">Lift Type Breakdown</mso:type.object.name>
    <mso:type.object.type rdf:resource="http://knowledge.microsoft.com/mso/type.property" />
    <mso:type.property.expected_type rdf:resource="http://knowledge.microsoft.com/mso/skiing.lift_type_breakdown" />
    <mso:type.property.max_cardinality rdf:datatype="http://www.w3.org/2001/XMLSchema#int">1</mso:type.property.max_cardinality>
    <mso:type.property.type rdf:resource="http://knowledge.microsoft.com/mso/skiing.ski_area" />
  </rdf:Description>
  <rdf:Description rdf:about="http://knowledge.microsoft.com/mso/skiing.ski_area.lifts">
    <mso:type.object.description xml:lang="en">Ski lifts used in this ski area, both present and historical.</mso:type.object.description>
    <mso:type.object.name xml:lang="en">Lifts</mso:type.object.name>
    <mso:type.object.type rdf:resource="http://knowledge.microsoft.com/mso/type.property" />
    <mso:type.property.expected_type rdf:resource="http://knowledge.microsoft.com/mso/skiing.ski_lift" />
    <mso:type.property.type rdf:resource="http://knowledge.microsoft.com/mso/skiing.ski_area" />
  </rdf:Description>
  <rdf:Description rdf:about="http://knowledge.microsoft.com/mso/skiing.ski_area.lifts_description">
    <mso:type.object.description xml:lang="en">Property relating an mso:skiing.ski_area to the text description of its ski lifts.</mso:type.object.description>
    <mso:type.object.name xml:lang="en">Lists Description</mso:type.object.name>
    <mso:type.object.type rdf:resource="http://knowledge.microsoft.com/mso/type.property" />
    <mso:type.property.expected_type rdf:resource="http://knowledge.microsoft.com/mso/type.text" />
    <mso:type.property.max_cardinality rdf:datatype="http://www.w3.org/2001/XMLSchema#int">1</mso:type.property.max_cardinality>
    <mso:type.property.type rdf:resource="http://knowledge.microsoft.com/mso/skiing.ski_area" />
  </rdf:Description>
  <rdf:Description rdf:about="http://knowledge.microsoft.com/mso/skiing.ski_area.lodges">
    <mso:type.object.description xml:lang="en">Ski lodges in this ski area.</mso:type.object.description>
    <mso:type.object.name xml:lang="en">Lodges</mso:type.object.name>
    <mso:type.object.type rdf:resource="http://knowledge.microsoft.com/mso/type.property" />
    <mso:type.property.expected_type rdf:resource="http://knowledge.microsoft.com/mso/skiing.ski_lodge" />
    <mso:type.property.type rdf:resource="http://knowledge.microsoft.com/mso/skiing.ski_area" />
  </rdf:Description>
  <rdf:Description rdf:about="http://knowledge.microsoft.com/mso/skiing.ski_area.longest_run">
    <mso:type.object.description xml:lang="en">Property relating an mso:skiing.ski_area to the length of the longest run.</mso:type.object.description>
    <mso:type.object.name xml:lang="en">Longest Run</mso:type.object.name>
    <mso:type.object.type rdf:resource="http://knowledge.microsoft.com/mso/type.property" />
    <mso:type.property.expected_type rdf:resource="http://knowledge.microsoft.com/mso/type.decimal" />
    <mso:type.property.max_cardinality rdf:datatype="http://www.w3.org/2001/XMLSchema#int">1</mso:type.property.max_cardinality>
    <mso:type.property.type rdf:resource="http://knowledge.microsoft.com/mso/skiing.ski_area" />
    <mso:type.property.unit rdf:resource="http://knowledge.microsoft.com/mso/type.unit.meter" />
  </rdf:Description>
  <rdf:Description rdf:about="http://knowledge.microsoft.com/mso/skiing.ski_area.longest_run_time">
    <mso:type.object.description xml:lang="en">Property relating an mso:skiing.ski_area to the average time to travel down the longest run.</mso:type.object.description>
    <mso:type.object.name xml:lang="en">Longest Run Time</mso:type.object.name>
    <mso:type.object.type rdf:resource="http://knowledge.microsoft.com/mso/type.property" />
    <mso:type.property.expected_type rdf:resource="http://knowledge.microsoft.com/mso/type.decimal" />
    <mso:type.property.max_cardinality rdf:datatype="http://www.w3.org/2001/XMLSchema#int">1</mso:type.property.max_cardinality>
    <mso:type.property.type rdf:resource="http://knowledge.microsoft.com/mso/skiing.ski_area" />
    <mso:type.property.unit rdf:resource="http://knowledge.microsoft.com/mso/type.unit.minute" />
  </rdf:Description>
  <rdf:Description rdf:about="http://knowledge.microsoft.com/mso/skiing.ski_area.number_lift">
    <mso:type.object.description xml:lang="en">Property relating an mso:skiing.ski_area to the number of lifts available in the area.</mso:type.object.description>
    <mso:type.object.name xml:lang="en">Lifts</mso:type.object.name>
    <mso:type.object.type rdf:resource="http://knowledge.microsoft.com/mso/type.property" />
    <mso:type.property.expected_type rdf:resource="http://knowledge.microsoft.com/mso/measurement_unit.dated_float" />
    <mso:type.property.max_cardinality rdf:datatype="http://www.w3.org/2001/XMLSchema#int">1</mso:type.property.max_cardinality>
    <mso:type.property.type rdf:resource="http://knowledge.microsoft.com/mso/skiing.ski_area" />
  </rdf:Description>
  <rdf:Description rdf:about="http://knowledge.microsoft.com/mso/skiing.ski_area.number_of_runs">
    <mso:type.object.description xml:lang="en">The total number of ski runs in this ski area.</mso:type.object.description>
    <mso:type.object.name xml:lang="en">Number of runs</mso:type.object.name>
    <mso:type.object.type rdf:resource="http://knowledge.microsoft.com/mso/type.property" />
    <mso:type.property.expected_type rdf:resource="http://knowledge.microsoft.com/mso/type.decimal" />
    <mso:type.property.max_cardinality rdf:datatype="http://www.w3.org/2001/XMLSchema#int">1</mso:type.property.max_cardinality>
    <mso:type.property.type rdf:resource="http://knowledge.microsoft.com/mso/skiing.ski_area" />
  </rdf:Description>
  <rdf:Description rdf:about="http://knowledge.microsoft.com/mso/skiing.ski_area.onslope_lower_depth">
    <mso:type.object.description xml:lang="en">Property relating an mso:skiing.ski_area to the lowest amount of snow for the area.</mso:type.object.description>
    <mso:type.object.name xml:lang="en">Lowest Depth Onslope</mso:type.object.name>
    <mso:type.object.type rdf:resource="http://knowledge.microsoft.com/mso/type.property" />
    <mso:type.property.expected_type rdf:resource="http://knowledge.microsoft.com/mso/type.decimal" />
    <mso:type.property.type rdf:resource="http://knowledge.microsoft.com/mso/skiing.ski_area" />
    <mso:type.property.unit rdf:resource="http://knowledge.microsoft.com/mso/type.unit.centimeter" />
  </rdf:Description>
  <rdf:Description rdf:about="http://knowledge.microsoft.com/mso/skiing.ski_area.open_days_year">
    <mso:type.object.description xml:lang="en">Property relating an mso:skiing.ski_area to the number of days the area was open for a given year.</mso:type.object.description>
    <mso:type.object.name xml:lang="en">Open Days for a Year</mso:type.object.name>
    <mso:type.object.type rdf:resource="http://knowledge.microsoft.com/mso/type.property" />
    <mso:type.property.expected_type rdf:resource="http://knowledge.microsoft.com/mso/measurement_unit.dated_float" />
    <mso:type.property.type rdf:resource="http://knowledge.microsoft.com/mso/skiing.ski_area" />
  </rdf:Description>
  <rdf:Description rdf:about="http://knowledge.microsoft.com/mso/skiing.ski_area.open_percentage">
    <mso:type.object.description xml:lang="en">Property relating an mso:skiing.ski_area to the percentage rate that the ski area is open.</mso:type.object.description>
    <mso:type.object.name xml:lang="en">Open Percentage</mso:type.object.name>
    <mso:type.object.type rdf:resource="http://knowledge.microsoft.com/mso/type.property" />
    <mso:type.property.expected_type rdf:resource="http://knowledge.microsoft.com/mso/measurement_unit.dated_percentage" />
    <mso:type.property.type rdf:resource="http://knowledge.microsoft.com/mso/skiing.ski_area" />
  </rdf:Description>
  <rdf:Description rdf:about="http://knowledge.microsoft.com/mso/skiing.ski_area.opening_date">
    <mso:type.object.description xml:lang="en">The date this ski area first opened.</mso:type.object.description>
    <mso:type.object.name xml:lang="en">Opening Date</mso:type.object.name>
    <mso:type.object.type rdf:resource="http://knowledge.microsoft.com/mso/type.property" />
    <mso:type.property.expected_type rdf:resource="http://knowledge.microsoft.com/mso/type.datetime" />
    <mso:type.property.max_cardinality rdf:datatype="http://www.w3.org/2001/XMLSchema#int">1</mso:type.property.max_cardinality>
    <mso:type.property.type rdf:resource="http://knowledge.microsoft.com/mso/skiing.ski_area" />
  </rdf:Description>
  <rdf:Description rdf:about="http://knowledge.microsoft.com/mso/skiing.ski_area.owner">
    <mso:type.object.description xml:lang="en">Past and present owners of this ski area.</mso:type.object.description>
    <mso:type.object.name xml:lang="en">Owners</mso:type.object.name>
    <mso:type.object.type rdf:resource="http://knowledge.microsoft.com/mso/type.property" />
    <mso:type.property.expected_type rdf:resource="http://knowledge.microsoft.com/mso/skiing.ski_area_ownership" />
    <mso:type.property.type rdf:resource="http://knowledge.microsoft.com/mso/skiing.ski_area" />
  </rdf:Description>
  <rdf:Description rdf:about="http://knowledge.microsoft.com/mso/skiing.ski_area.pass_pricing">
    <mso:type.object.description xml:lang="en">Virtual property relating an mso:skiing.ski_area to the prices of the passes the area accepts.</mso:type.object.description>
    <mso:type.object.name xml:lang="en">Pass Pricing</mso:type.object.name>
    <mso:type.object.type rdf:resource="http://knowledge.microsoft.com/mso/type.property" />
    <mso:type.object.type rdf:resource="http://knowledge.microsoft.com/mso/type.virtual_property" />
    <mso:type.property.expected_type rdf:resource="http://knowledge.microsoft.com/mso/common.pricing_relationship" />
    <mso:type.property.type rdf:resource="http://knowledge.microsoft.com/mso/skiing.ski_area" />
  </rdf:Description>
  <rdf:Description rdf:about="http://knowledge.microsoft.com/mso/skiing.ski_area.peak_lift_ticket">
    <mso:type.object.description xml:lang="en">Property relating an mso:skiing.ski_area to the mso:common.pricing_relationship that contains the data of the area's lift ticket prices during the peak season.</mso:type.object.description>
    <mso:type.object.name xml:lang="en">Peak Lift Ticket Prices</mso:type.object.name>
    <mso:type.object.type rdf:resource="http://knowledge.microsoft.com/mso/type.property" />
    <mso:type.property.expected_type rdf:resource="http://knowledge.microsoft.com/mso/common.pricing_relationship" />
    <mso:type.property.type rdf:resource="http://knowledge.microsoft.com/mso/skiing.ski_area" />
  </rdf:Description>
  <rdf:Description rdf:about="http://knowledge.microsoft.com/mso/skiing.ski_area.runs_by_difficulty">
    <mso:type.object.description xml:lang="en">Property relating an mso:skiing.ski_area to the mso: relationship that collects data on the level of difficulty of the ski runs and their numbers for the area.</mso:type.object.description>
    <mso:type.object.name xml:lang="en">Runs by Difficulty</mso:type.object.name>
    <mso:type.object.type rdf:resource="http://knowledge.microsoft.com/mso/type.property" />
    <mso:type.property.expected_type rdf:resource="http://knowledge.microsoft.com/mso/skiing.ski_area_run_difficulty" />
    <mso:type.property.type rdf:resource="http://knowledge.microsoft.com/mso/skiing.ski_area" />
  </rdf:Description>
  <rdf:Description rdf:about="http://knowledge.microsoft.com/mso/skiing.ski_area.ski_pass">
    <mso:type.object.description xml:lang="en">Property relating an mso:skiing.ski_area to the mso:skiing.ski_pass the area accepts.</mso:type.object.description>
    <mso:type.object.name xml:lang="en">Ski Pass</mso:type.object.name>
    <mso:type.object.type rdf:resource="http://knowledge.microsoft.com/mso/type.property" />
    <mso:type.property.expected_type rdf:resource="http://knowledge.microsoft.com/mso/skiing.ski_pass" />
    <mso:type.property.type rdf:resource="http://knowledge.microsoft.com/mso/skiing.ski_area" />
  </rdf:Description>
  <rdf:Description rdf:about="http://knowledge.microsoft.com/mso/skiing.ski_area.skiable_area">
    <mso:type.object.description xml:lang="en">The total skiable area of this ski area.</mso:type.object.description>
    <mso:type.object.name xml:lang="en">Skiable area</mso:type.object.name>
    <mso:type.object.type rdf:resource="http://knowledge.microsoft.com/mso/type.property" />
    <mso:type.property.expected_type rdf:resource="http://knowledge.microsoft.com/mso/type.decimal" />
    <mso:type.property.max_cardinality rdf:datatype="http://www.w3.org/2001/XMLSchema#int">1</mso:type.property.max_cardinality>
    <mso:type.property.type rdf:resource="http://knowledge.microsoft.com/mso/skiing.ski_area" />
    <mso:type.property.unit rdf:resource="http://knowledge.microsoft.com/mso/type.unit.square_kilometer" />
  </rdf:Description>
  <rdf:Description rdf:about="http://knowledge.microsoft.com/mso/skiing.ski_area.snowfall">
    <mso:type.object.description xml:lang="en">Yearly amount of snowfall in a season (in centimeters with a start and end date for each season measured).</mso:type.object.description>
    <mso:type.object.name xml:lang="en">Snowfall</mso:type.object.name>
    <mso:type.object.type rdf:resource="http://knowledge.microsoft.com/mso/type.property" />
    <mso:type.property.expected_type rdf:resource="http://knowledge.microsoft.com/mso/skiing.yearly_snowfall" />
    <mso:type.property.type rdf:resource="http://knowledge.microsoft.com/mso/skiing.ski_area" />
  </rdf:Description>
  <rdf:Description rdf:about="http://knowledge.microsoft.com/mso/skiing.ski_area.terrain_park_breakdown">
    <mso:type.object.description xml:lang="en">Property relating an mso:skiing.ski_area to the mso:skiing.terrain_park_breakdown for the area. The data includes the total number of terrain parks and the number open.</mso:type.object.description>
    <mso:type.object.name xml:lang="en">Terrain Park Breakdown</mso:type.object.name>
    <mso:type.object.type rdf:resource="http://knowledge.microsoft.com/mso/type.property" />
    <mso:type.property.expected_type rdf:resource="http://knowledge.microsoft.com/mso/skiing.terrain_park_breakdown" />
    <mso:type.property.max_cardinality rdf:datatype="http://www.w3.org/2001/XMLSchema#int">1</mso:type.property.max_cardinality>
    <mso:type.property.type rdf:resource="http://knowledge.microsoft.com/mso/skiing.ski_area" />
  </rdf:Description>
  <rdf:Description rdf:about="http://knowledge.microsoft.com/mso/skiing.ski_area.top_elevation">
    <mso:type.object.description xml:lang="en">Highest elevation of the skiable area (in meters).</mso:type.object.description>
    <mso:type.object.name xml:lang="en">Top elevation</mso:type.object.name>
    <mso:type.object.type rdf:resource="http://knowledge.microsoft.com/mso/type.property" />
    <mso:type.property.expected_type rdf:resource="http://knowledge.microsoft.com/mso/type.decimal" />
    <mso:type.property.max_cardinality rdf:datatype="http://www.w3.org/2001/XMLSchema#int">1</mso:type.property.max_cardinality>
    <mso:type.property.type rdf:resource="http://knowledge.microsoft.com/mso/skiing.ski_area" />
    <mso:type.property.unit rdf:resource="http://knowledge.microsoft.com/mso/type.unit.meter" />
  </rdf:Description>
  <rdf:Description rdf:about="http://knowledge.microsoft.com/mso/skiing.ski_area.total_open_lift">
    <mso:type.object.description xml:lang="en">Property relating an mso:skiing.skiing.ski_area to the number of open lifts. This is the total number of open lifts.</mso:type.object.description>
    <mso:type.object.name xml:lang="en">Total Open Lifts</mso:type.object.name>
    <mso:type.object.type rdf:resource="http://knowledge.microsoft.com/mso/type.property" />
    <mso:type.property.expected_type rdf:resource="http://knowledge.microsoft.com/mso/type.decimal" />
    <mso:type.property.max_cardinality rdf:datatype="http://www.w3.org/2001/XMLSchema#int">1</mso:type.property.max_cardinality>
    <mso:type.property.type rdf:resource="http://knowledge.microsoft.com/mso/skiing.ski_area" />
  </rdf:Description>
  <rdf:Description rdf:about="http://knowledge.microsoft.com/mso/skiing.ski_area.uphill_capacity">
    <mso:type.object.description xml:lang="en">Property relating an mso:skiing.ski_area to the resort's uphill capacity. This is the number of skiers that can be transported to the top of the mountain at given time. This number is people per hour.</mso:type.object.description>
    <mso:type.object.name xml:lang="en">Uphill Capacity</mso:type.object.name>
    <mso:type.object.type rdf:resource="http://knowledge.microsoft.com/mso/type.property" />
    <mso:type.property.expected_type rdf:resource="http://knowledge.microsoft.com/mso/type.decimal" />
    <mso:type.property.max_cardinality rdf:datatype="http://www.w3.org/2001/XMLSchema#int">1</mso:type.property.max_cardinality>
    <mso:type.property.type rdf:resource="http://knowledge.microsoft.com/mso/skiing.ski_area" />
  </rdf:Description>
  <rdf:Description rdf:about="http://knowledge.microsoft.com/mso/skiing.ski_area.vertical_rise">
    <mso:type.object.description xml:lang="en">Property relating an mso:skiing.ski_resort to the resort's published vertical rise. Vertical rise is the difference in elevation between the top and bottom terminals of the resort's ski lift.</mso:type.object.description>
    <mso:type.object.name xml:lang="en">Vertical Rise</mso:type.object.name>
    <mso:type.object.type rdf:resource="http://knowledge.microsoft.com/mso/type.property" />
    <mso:type.property.expected_type rdf:resource="http://knowledge.microsoft.com/mso/type.decimal" />
    <mso:type.property.max_cardinality rdf:datatype="http://www.w3.org/2001/XMLSchema#int">1</mso:type.property.max_cardinality>
    <mso:type.property.type rdf:resource="http://knowledge.microsoft.com/mso/skiing.ski_area" />
    <mso:type.property.unit rdf:resource="http://knowledge.microsoft.com/mso/type.unit.meter" />
  </rdf:Description>
  <rdf:Description rdf:about="http://knowledge.microsoft.com/mso/skiing.ski_area_owner">
    <mso:type.object.name xml:lang="en">Ski Area Owner</mso:type.object.name>
    <mso:type.object.type rdf:resource="http://knowledge.microsoft.com/mso/type.type" />
    <mso:type.type.category rdf:resource="http://knowledge.microsoft.com/mso/type.category.primary_entity" />
    <mso:type.type.deprecation_info xml:lang="en">There is no need to reify owners of ski areas.  Use event.agent instead. DeprecatedBy:[REDMOND\ianiles] Successor:[mso:event.agent]</mso:type.type.deprecation_info>
    <mso:type.type.domain rdf:resource="http://knowledge.microsoft.com/mso/skiing" />
    <mso:type.type.includes rdf:resource="http://knowledge.microsoft.com/mso/type.object" />
  </rdf:Description>
  <rdf:Description rdf:about="http://knowledge.microsoft.com/mso/skiing.ski_area_ownership">
    <mso:type.object.name xml:lang="en">Ski Area Ownership</mso:type.object.name>
    <mso:type.object.type rdf:resource="http://knowledge.microsoft.com/mso/type.type" />
    <mso:type.type.category rdf:resource="http://knowledge.microsoft.com/mso/type.category.relationship" />
    <mso:type.type.deprecation_info xml:lang="en">Use common.ownership_relationship instead. DeprecatedBy:[REDMOND\ianiles] Successor:[mso:common.ownership_relationship]</mso:type.type.deprecation_info>
    <mso:type.type.domain rdf:resource="http://knowledge.microsoft.com/mso/skiing" />
    <mso:type.type.includes rdf:resource="http://knowledge.microsoft.com/mso/type.object" />
  </rdf:Description>
  <rdf:Description rdf:about="http://knowledge.microsoft.com/mso/skiing.ski_area_ownership.end_date">
    <mso:type.object.description xml:lang="en">The date after which this person or organization no longer owned the ski area.</mso:type.object.description>
    <mso:type.object.name xml:lang="en">End date</mso:type.object.name>
    <mso:type.object.type rdf:resource="http://knowledge.microsoft.com/mso/type.property" />
    <mso:type.property.deprecation_info xml:lang="en">Use common.ownership_relationship.end_date DeprecatedBy:[REDMOND\ianiles] Successor:[mso:common.ownership_relationship.end_date]</mso:type.property.deprecation_info>
    <mso:type.property.expected_type rdf:resource="http://knowledge.microsoft.com/mso/type.datetime" />
    <mso:type.property.max_cardinality rdf:datatype="http://www.w3.org/2001/XMLSchema#int">1</mso:type.property.max_cardinality>
    <mso:type.property.type rdf:resource="http://knowledge.microsoft.com/mso/skiing.ski_area_ownership" />
  </rdf:Description>
  <rdf:Description rdf:about="http://knowledge.microsoft.com/mso/skiing.ski_area_ownership.owner">
    <mso:type.object.description xml:lang="en">The person or organization that owns or owned this ski area.</mso:type.object.description>
    <mso:type.object.name xml:lang="en">Owner</mso:type.object.name>
    <mso:type.object.type rdf:resource="http://knowledge.microsoft.com/mso/type.property" />
    <mso:type.property.deprecation_info xml:lang="en">Use common.ownership_relationship.owner instead. DeprecatedBy:[REDMOND\ianiles] Successor:[mso:common.ownership_relationship.owner]</mso:type.property.deprecation_info>
    <mso:type.property.expected_type rdf:resource="http://knowledge.microsoft.com/mso/skiing.ski_area_owner" />
    <mso:type.property.max_cardinality rdf:datatype="http://www.w3.org/2001/XMLSchema#int">1</mso:type.property.max_cardinality>
    <mso:type.property.type rdf:resource="http://knowledge.microsoft.com/mso/skiing.ski_area_ownership" />
  </rdf:Description>
  <rdf:Description rdf:about="http://knowledge.microsoft.com/mso/skiing.ski_area_ownership.start_date">
    <mso:type.object.description xml:lang="en">The date at which this person or organization first owned the ski area.</mso:type.object.description>
    <mso:type.object.name xml:lang="en">Start date</mso:type.object.name>
    <mso:type.object.type rdf:resource="http://knowledge.microsoft.com/mso/type.property" />
    <mso:type.property.deprecation_info xml:lang="en">Use common.ownership_relationship.start_date instead. DeprecatedBy:[REDMOND\ianiles] Successor:[mso:common.ownership_relationship.start_date]</mso:type.property.deprecation_info>
    <mso:type.property.expected_type rdf:resource="http://knowledge.microsoft.com/mso/type.datetime" />
    <mso:type.property.max_cardinality rdf:datatype="http://www.w3.org/2001/XMLSchema#int">1</mso:type.property.max_cardinality>
    <mso:type.property.type rdf:resource="http://knowledge.microsoft.com/mso/skiing.ski_area_ownership" />
  </rdf:Description>
  <rdf:Description rdf:about="http://knowledge.microsoft.com/mso/skiing.ski_area_run_difficulty">
    <mso:type.object.description xml:lang="en">Relationship collecting the data on an mso:skiing.ski_area's mso:skiing.ski_runs. This includes the numbers of the runs by difficulty type.</mso:type.object.description>
    <mso:type.object.name xml:lang="en">Ski Area Run Breakdown Relationship</mso:type.object.name>
    <mso:type.object.type rdf:resource="http://knowledge.microsoft.com/mso/type.type" />
    <mso:type.type.category rdf:resource="http://knowledge.microsoft.com/mso/type.category.relationship" />
    <mso:type.type.domain rdf:resource="http://knowledge.microsoft.com/mso/skiing" />
    <mso:type.type.includes rdf:resource="http://knowledge.microsoft.com/mso/type.object" />
  </rdf:Description>
  <rdf:Description rdf:about="http://knowledge.microsoft.com/mso/skiing.ski_area_run_difficulty.difficulty">
    <mso:type.object.description xml:lang="en">Property relating an mso:skiing.ski_area_run_difficulty to the mso:common.difficulty_level of the runs.</mso:type.object.description>
    <mso:type.object.name xml:lang="en">Difficulty</mso:type.object.name>
    <mso:type.object.type rdf:resource="http://knowledge.microsoft.com/mso/type.property" />
    <mso:type.property.expected_type rdf:resource="http://knowledge.microsoft.com/mso/skiing.run_rating" />
    <mso:type.property.max_cardinality rdf:datatype="http://www.w3.org/2001/XMLSchema#int">1</mso:type.property.max_cardinality>
    <mso:type.property.type rdf:resource="http://knowledge.microsoft.com/mso/skiing.ski_area_run_difficulty" />
  </rdf:Description>
  <rdf:Description rdf:about="http://knowledge.microsoft.com/mso/skiing.ski_area_run_difficulty.number">
    <mso:type.object.description xml:lang="en">Property relating an mso:skiing.ski_area_run_difficulty to the number of runs at the given mso:common.difficulty_level.</mso:type.object.description>
    <mso:type.object.name xml:lang="en">Number</mso:type.object.name>
    <mso:type.object.type rdf:resource="http://knowledge.microsoft.com/mso/type.property" />
    <mso:type.property.expected_type rdf:resource="http://knowledge.microsoft.com/mso/type.decimal" />
    <mso:type.property.max_cardinality rdf:datatype="http://www.w3.org/2001/XMLSchema#int">1</mso:type.property.max_cardinality>
    <mso:type.property.type rdf:resource="http://knowledge.microsoft.com/mso/skiing.ski_area_run_difficulty" />
  </rdf:Description>
  <rdf:Description rdf:about="http://knowledge.microsoft.com/mso/skiing.ski_area_run_difficulty.open">
    <mso:type.object.description xml:lang="en">Property relating an mso:skiing.ski_area_run_difficulty to the number of open runs of this difficulty level for the mso:skiing.ski_area.</mso:type.object.description>
    <mso:type.object.name xml:lang="en">Number Open</mso:type.object.name>
    <mso:type.object.type rdf:resource="http://knowledge.microsoft.com/mso/type.property" />
    <mso:type.property.expected_type rdf:resource="http://knowledge.microsoft.com/mso/type.decimal" />
    <mso:type.property.max_cardinality rdf:datatype="http://www.w3.org/2001/XMLSchema#int">1</mso:type.property.max_cardinality>
    <mso:type.property.type rdf:resource="http://knowledge.microsoft.com/mso/skiing.ski_area_run_difficulty" />
  </rdf:Description>
  <rdf:Description rdf:about="http://knowledge.microsoft.com/mso/skiing.ski_area_run_difficulty.total_length">
    <mso:type.object.description xml:lang="en">Property relating an mso:skiing.ski_area_run_difficulty relationship to the total length of the runs for the given difficulty level.</mso:type.object.description>
    <mso:type.object.name xml:lang="en">Total Length</mso:type.object.name>
    <mso:type.object.type rdf:resource="http://knowledge.microsoft.com/mso/type.property" />
    <mso:type.property.expected_type rdf:resource="http://knowledge.microsoft.com/mso/type.decimal" />
    <mso:type.property.max_cardinality rdf:datatype="http://www.w3.org/2001/XMLSchema#int">1</mso:type.property.max_cardinality>
    <mso:type.property.type rdf:resource="http://knowledge.microsoft.com/mso/skiing.ski_area_run_difficulty" />
    <mso:type.property.unit rdf:resource="http://knowledge.microsoft.com/mso/type.unit.meter" />
  </rdf:Description>
  <rdf:Description rdf:about="http://knowledge.microsoft.com/mso/skiing.ski_area_run_difficulty.total_length_open">
    <mso:type.object.description xml:lang="en">Property relating an mso:skiing.ski_area_run_difficulty relationship to the total length of the open runs for the given difficulty level.</mso:type.object.description>
    <mso:type.object.name xml:lang="en">Total Open Length</mso:type.object.name>
    <mso:type.object.type rdf:resource="http://knowledge.microsoft.com/mso/type.property" />
    <mso:type.property.expected_type rdf:resource="http://knowledge.microsoft.com/mso/type.decimal" />
    <mso:type.property.max_cardinality rdf:datatype="http://www.w3.org/2001/XMLSchema#int">1</mso:type.property.max_cardinality>
    <mso:type.property.type rdf:resource="http://knowledge.microsoft.com/mso/skiing.ski_area_run_difficulty" />
    <mso:type.property.unit rdf:resource="http://knowledge.microsoft.com/mso/type.unit.meter" />
  </rdf:Description>
  <rdf:Description rdf:about="http://knowledge.microsoft.com/mso/skiing.ski_lift">
    <mso:type.object.description xml:lang="en">Primary entity representing the collection of all ski lifts. Ski lifts are the cabled devices that carry skiers up a hill.</mso:type.object.description>
    <mso:type.object.name xml:lang="en">Ski Lift</mso:type.object.name>
    <mso:type.object.type rdf:resource="http://knowledge.microsoft.com/mso/type.type" />
    <mso:type.type.category rdf:resource="http://knowledge.microsoft.com/mso/type.category.primary_entity" />
    <mso:type.type.domain rdf:resource="http://knowledge.microsoft.com/mso/skiing" />
    <mso:type.type.includes rdf:resource="http://knowledge.microsoft.com/mso/type.object" />
  </rdf:Description>
  <rdf:Description rdf:about="http://knowledge.microsoft.com/mso/skiing.ski_lift.base_elevation">
    <mso:type.object.description xml:lang="en">The elevation at the base of the lift.</mso:type.object.description>
    <mso:type.object.name xml:lang="en">Base Elevation</mso:type.object.name>
    <mso:type.object.type rdf:resource="http://knowledge.microsoft.com/mso/type.property" />
    <mso:type.property.expected_type rdf:resource="http://knowledge.microsoft.com/mso/type.decimal" />
    <mso:type.property.max_cardinality rdf:datatype="http://www.w3.org/2001/XMLSchema#int">1</mso:type.property.max_cardinality>
    <mso:type.property.type rdf:resource="http://knowledge.microsoft.com/mso/skiing.ski_lift" />
    <mso:type.property.unit rdf:resource="http://knowledge.microsoft.com/mso/type.unit.meter" />
  </rdf:Description>
  <rdf:Description rdf:about="http://knowledge.microsoft.com/mso/skiing.ski_lift.lift_type">
    <mso:type.object.description xml:lang="en">The type of lift this is.</mso:type.object.description>
    <mso:type.object.name xml:lang="en">Lift type</mso:type.object.name>
    <mso:type.object.type rdf:resource="http://knowledge.microsoft.com/mso/type.property" />
    <mso:type.property.expected_type rdf:resource="http://knowledge.microsoft.com/mso/skiing.lift_tenure" />
    <mso:type.property.type rdf:resource="http://knowledge.microsoft.com/mso/skiing.ski_lift" />
  </rdf:Description>
  <rdf:Description rdf:about="http://knowledge.microsoft.com/mso/skiing.ski_lift.runs_served">
    <mso:type.object.description xml:lang="en">The ski run or ski runs served by this lift.</mso:type.object.description>
    <mso:type.object.name xml:lang="en">Runs served</mso:type.object.name>
    <mso:type.object.type rdf:resource="http://knowledge.microsoft.com/mso/type.property" />
    <mso:type.property.expected_type rdf:resource="http://knowledge.microsoft.com/mso/skiing.ski_run" />
    <mso:type.property.type rdf:resource="http://knowledge.microsoft.com/mso/skiing.ski_lift" />
  </rdf:Description>
  <rdf:Description rdf:about="http://knowledge.microsoft.com/mso/skiing.ski_lift.top_elevation">
    <mso:type.object.description xml:lang="en">The elevation at the top of the lift.</mso:type.object.description>
    <mso:type.object.name xml:lang="en">Top Elevation</mso:type.object.name>
    <mso:type.object.type rdf:resource="http://knowledge.microsoft.com/mso/type.property" />
    <mso:type.property.expected_type rdf:resource="http://knowledge.microsoft.com/mso/type.decimal" />
    <mso:type.property.max_cardinality rdf:datatype="http://www.w3.org/2001/XMLSchema#int">1</mso:type.property.max_cardinality>
    <mso:type.property.type rdf:resource="http://knowledge.microsoft.com/mso/skiing.ski_lift" />
    <mso:type.property.unit rdf:resource="http://knowledge.microsoft.com/mso/type.unit.meter" />
  </rdf:Description>
  <rdf:Description rdf:about="http://knowledge.microsoft.com/mso/skiing.ski_lift_manufacturer">
    <mso:type.object.description xml:lang="en">Primary entity representing the collection of all ski lift manufacturers.</mso:type.object.description>
    <mso:type.object.name xml:lang="en">Ski Lift Manufacturer</mso:type.object.name>
    <mso:type.object.type rdf:resource="http://knowledge.microsoft.com/mso/type.type" />
    <mso:type.type.category rdf:resource="http://knowledge.microsoft.com/mso/type.category.primary_entity" />
    <mso:type.type.domain rdf:resource="http://knowledge.microsoft.com/mso/skiing" />
    <mso:type.type.includes rdf:resource="http://knowledge.microsoft.com/mso/business.consumer_company" />
    <mso:type.type.includes rdf:resource="http://knowledge.microsoft.com/mso/business.employer" />
    <mso:type.type.includes rdf:resource="http://knowledge.microsoft.com/mso/business.operation" />
    <mso:type.type.includes rdf:resource="http://knowledge.microsoft.com/mso/common.group" />
    <mso:type.type.includes rdf:resource="http://knowledge.microsoft.com/mso/event.agent" />
    <mso:type.type.includes rdf:resource="http://knowledge.microsoft.com/mso/media_common.cataloged_instance" />
    <mso:type.type.includes rdf:resource="http://knowledge.microsoft.com/mso/organization.organization" />
    <mso:type.type.includes rdf:resource="http://knowledge.microsoft.com/mso/ratings.rated_entity" />
    <mso:type.type.includes rdf:resource="http://knowledge.microsoft.com/mso/type.object" />
  </rdf:Description>
  <rdf:Description rdf:about="http://knowledge.microsoft.com/mso/skiing.ski_lodge">
    <mso:type.object.description xml:lang="en">Primary entity representing the collection of all ski lodges. Ski lodges are the hotels in ski resorts.</mso:type.object.description>
    <mso:type.object.name xml:lang="en">Ski Lodge</mso:type.object.name>
    <mso:type.object.type rdf:resource="http://knowledge.microsoft.com/mso/type.type" />
    <mso:type.type.category rdf:resource="http://knowledge.microsoft.com/mso/type.category.primary_entity" />
    <mso:type.type.domain rdf:resource="http://knowledge.microsoft.com/mso/skiing" />
    <mso:type.type.includes rdf:resource="http://knowledge.microsoft.com/mso/architecture.building" />
    <mso:type.type.includes rdf:resource="http://knowledge.microsoft.com/mso/architecture.structure" />
    <mso:type.type.includes rdf:resource="http://knowledge.microsoft.com/mso/local.accommodation" />
    <mso:type.type.includes rdf:resource="http://knowledge.microsoft.com/mso/local.entity" />
    <mso:type.type.includes rdf:resource="http://knowledge.microsoft.com/mso/location.location" />
    <mso:type.type.includes rdf:resource="http://knowledge.microsoft.com/mso/media_common.cataloged_instance" />
    <mso:type.type.includes rdf:resource="http://knowledge.microsoft.com/mso/media_common.creative_work" />
    <mso:type.type.includes rdf:resource="http://knowledge.microsoft.com/mso/media_common.subject" />
    <mso:type.type.includes rdf:resource="http://knowledge.microsoft.com/mso/projects.project_focus" />
    <mso:type.type.includes rdf:resource="http://knowledge.microsoft.com/mso/ratings.rated_entity" />
    <mso:type.type.includes rdf:resource="http://knowledge.microsoft.com/mso/type.object" />
  </rdf:Description>
  <rdf:Description rdf:about="http://knowledge.microsoft.com/mso/skiing.ski_lodge.restaurants">
    <mso:type.object.description xml:lang="en">Restaurants in this lodge</mso:type.object.description>
    <mso:type.object.name xml:lang="en">Restaurants</mso:type.object.name>
    <mso:type.object.type rdf:resource="http://knowledge.microsoft.com/mso/type.property" />
    <mso:type.property.expected_type rdf:resource="http://knowledge.microsoft.com/mso/local.restaurant" />
    <mso:type.property.subproperty rdf:resource="http://knowledge.microsoft.com/mso/local.accommodation.restaurants" />
    <mso:type.property.type rdf:resource="http://knowledge.microsoft.com/mso/skiing.ski_lodge" />
  </rdf:Description>
  <rdf:Description rdf:about="http://knowledge.microsoft.com/mso/skiing.ski_pass">
    <mso:type.object.alias xml:lang="en">Ski Season Pass</mso:type.object.alias>
    <mso:type.object.description xml:lang="en">Primary entity representing the collection of all ski passes. Ski passes are the passes issued for mso:ski_areas that offer discounted prices on lift tickets.</mso:type.object.description>
    <mso:type.object.name xml:lang="en">Ski Pass</mso:type.object.name>
    <mso:type.object.type rdf:resource="http://knowledge.microsoft.com/mso/type.type" />
    <mso:type.type.category rdf:resource="http://knowledge.microsoft.com/mso/type.category.primary_entity" />
    <mso:type.type.domain rdf:resource="http://knowledge.microsoft.com/mso/skiing" />
    <mso:type.type.includes rdf:resource="http://knowledge.microsoft.com/mso/event.season_pass" />
    <mso:type.type.includes rdf:resource="http://knowledge.microsoft.com/mso/event.ticket" />
    <mso:type.type.includes rdf:resource="http://knowledge.microsoft.com/mso/type.object" />
  </rdf:Description>
  <rdf:Description rdf:about="http://knowledge.microsoft.com/mso/skiing.ski_run">
    <mso:type.object.alias xml:lang="en">Piste</mso:type.object.alias>
    <mso:type.object.description xml:lang="en">Primary entity representing the collection of all ski runs. Ski runs are the paths down a mountain for skiing or snowboarding.</mso:type.object.description>
    <mso:type.object.name xml:lang="en">Ski Run</mso:type.object.name>
    <mso:type.object.type rdf:resource="http://knowledge.microsoft.com/mso/type.type" />
    <mso:type.type.category rdf:resource="http://knowledge.microsoft.com/mso/type.category.primary_entity" />
    <mso:type.type.domain rdf:resource="http://knowledge.microsoft.com/mso/skiing" />
    <mso:type.type.includes rdf:resource="http://knowledge.microsoft.com/mso/type.object" />
  </rdf:Description>
  <rdf:Description rdf:about="http://knowledge.microsoft.com/mso/skiing.ski_run.date_closed">
    <mso:type.object.description xml:lang="en">The date this ski run was closed permanently</mso:type.object.description>
    <mso:type.object.name xml:lang="en">Date closed</mso:type.object.name>
    <mso:type.object.type rdf:resource="http://knowledge.microsoft.com/mso/type.property" />
    <mso:type.property.expected_type rdf:resource="http://knowledge.microsoft.com/mso/type.datetime" />
    <mso:type.property.max_cardinality rdf:datatype="http://www.w3.org/2001/XMLSchema#int">1</mso:type.property.max_cardinality>
    <mso:type.property.type rdf:resource="http://knowledge.microsoft.com/mso/skiing.ski_run" />
  </rdf:Description>
  <rdf:Description rdf:about="http://knowledge.microsoft.com/mso/skiing.ski_run.date_opened">
    <mso:type.object.description xml:lang="en">The date this ski run was first opened</mso:type.object.description>
    <mso:type.object.name xml:lang="en">Date opened</mso:type.object.name>
    <mso:type.object.type rdf:resource="http://knowledge.microsoft.com/mso/type.property" />
    <mso:type.property.expected_type rdf:resource="http://knowledge.microsoft.com/mso/type.datetime" />
    <mso:type.property.max_cardinality rdf:datatype="http://www.w3.org/2001/XMLSchema#int">1</mso:type.property.max_cardinality>
    <mso:type.property.type rdf:resource="http://knowledge.microsoft.com/mso/skiing.ski_run" />
  </rdf:Description>
  <rdf:Description rdf:about="http://knowledge.microsoft.com/mso/skiing.ski_run.rating">
    <mso:type.object.description xml:lang="en">The difficulty rating of this ski run.</mso:type.object.description>
    <mso:type.object.name xml:lang="en">Rating</mso:type.object.name>
    <mso:type.object.type rdf:resource="http://knowledge.microsoft.com/mso/type.property" />
    <mso:type.property.expected_type rdf:resource="http://knowledge.microsoft.com/mso/skiing.run_rating" />
    <mso:type.property.type rdf:resource="http://knowledge.microsoft.com/mso/skiing.ski_run" />
  </rdf:Description>
  <rdf:Description rdf:about="http://knowledge.microsoft.com/mso/skiing.ski_run.ski_area">
    <mso:type.object.description xml:lang="en">The ski area that this ski run is in</mso:type.object.description>
    <mso:type.object.name xml:lang="en">Ski area</mso:type.object.name>
    <mso:type.object.type rdf:resource="http://knowledge.microsoft.com/mso/type.property" />
    <mso:type.property.expected_type rdf:resource="http://knowledge.microsoft.com/mso/skiing.ski_area" />
    <mso:type.property.max_cardinality rdf:datatype="http://www.w3.org/2001/XMLSchema#int">1</mso:type.property.max_cardinality>
    <mso:type.property.type rdf:resource="http://knowledge.microsoft.com/mso/skiing.ski_run" />
  </rdf:Description>
  <rdf:Description rdf:about="http://knowledge.microsoft.com/mso/skiing.terrain_park_breakdown">
    <mso:type.object.description xml:lang="en">Relationship collecting data on a mso:skiing.ski_area's terrain parks. Terrain parks are the is an outdoor recreation area containing terrain that allows skiers, snowboarders and snowbikers to perform tricks.</mso:type.object.description>
    <mso:type.object.name xml:lang="en">Terrain Park Breakdown</mso:type.object.name>
    <mso:type.object.type rdf:resource="http://knowledge.microsoft.com/mso/type.type" />
    <mso:type.type.category rdf:resource="http://knowledge.microsoft.com/mso/type.category.relationship" />
    <mso:type.type.domain rdf:resource="http://knowledge.microsoft.com/mso/skiing" />
    <mso:type.type.includes rdf:resource="http://knowledge.microsoft.com/mso/type.object" />
  </rdf:Description>
  <rdf:Description rdf:about="http://knowledge.microsoft.com/mso/skiing.terrain_park_breakdown.number">
    <mso:type.object.description xml:lang="en">Property relating an mso:skiing.terrain_park_breakdown to the total number of terrain parks the mso:skiing.ski_area contains.</mso:type.object.description>
    <mso:type.object.name xml:lang="en">Total</mso:type.object.name>
    <mso:type.object.type rdf:resource="http://knowledge.microsoft.com/mso/type.property" />
    <mso:type.property.expected_type rdf:resource="http://knowledge.microsoft.com/mso/type.decimal" />
    <mso:type.property.max_cardinality rdf:datatype="http://www.w3.org/2001/XMLSchema#int">1</mso:type.property.max_cardinality>
    <mso:type.property.type rdf:resource="http://knowledge.microsoft.com/mso/skiing.terrain_park_breakdown" />
  </rdf:Description>
  <rdf:Description rdf:about="http://knowledge.microsoft.com/mso/skiing.terrain_park_breakdown.number_half_pipes">
    <mso:type.object.description xml:lang="en">Property relating an mso:skiing.terrain_park_breakdown to the number of half-pipes in the terrain parks.</mso:type.object.description>
    <mso:type.object.name xml:lang="en">Half-Pipes</mso:type.object.name>
    <mso:type.object.type rdf:resource="http://knowledge.microsoft.com/mso/type.property" />
    <mso:type.property.expected_type rdf:resource="http://knowledge.microsoft.com/mso/type.decimal" />
    <mso:type.property.max_cardinality rdf:datatype="http://www.w3.org/2001/XMLSchema#int">1</mso:type.property.max_cardinality>
    <mso:type.property.type rdf:resource="http://knowledge.microsoft.com/mso/skiing.terrain_park_breakdown" />
  </rdf:Description>
  <rdf:Description rdf:about="http://knowledge.microsoft.com/mso/skiing.terrain_park_breakdown.number_half_pipes_open">
    <mso:type.object.description xml:lang="en">Property relating an mso:skiing.terrain_park_breakdown to the total number of half pipes open in the mso:skiing.ski_area's terrain parks.</mso:type.object.description>
    <mso:type.object.name xml:lang="en">Number of Open Half Pipes</mso:type.object.name>
    <mso:type.object.type rdf:resource="http://knowledge.microsoft.com/mso/type.property" />
    <mso:type.property.expected_type rdf:resource="http://knowledge.microsoft.com/mso/type.decimal" />
    <mso:type.property.max_cardinality rdf:datatype="http://www.w3.org/2001/XMLSchema#int">1</mso:type.property.max_cardinality>
    <mso:type.property.type rdf:resource="http://knowledge.microsoft.com/mso/skiing.terrain_park_breakdown" />
  </rdf:Description>
  <rdf:Description rdf:about="http://knowledge.microsoft.com/mso/skiing.terrain_park_breakdown.number_jumps">
    <mso:type.object.description xml:lang="en">Property relating an mso:skiing.terrain_park_breakdown to the total number of jumps in the mso:skiing.ski_area's terrain parks.</mso:type.object.description>
    <mso:type.object.name xml:lang="en">Number of Jumps</mso:type.object.name>
    <mso:type.object.type rdf:resource="http://knowledge.microsoft.com/mso/type.property" />
    <mso:type.property.expected_type rdf:resource="http://knowledge.microsoft.com/mso/type.decimal" />
    <mso:type.property.max_cardinality rdf:datatype="http://www.w3.org/2001/XMLSchema#int">1</mso:type.property.max_cardinality>
    <mso:type.property.type rdf:resource="http://knowledge.microsoft.com/mso/skiing.terrain_park_breakdown" />
  </rdf:Description>
  <rdf:Description rdf:about="http://knowledge.microsoft.com/mso/skiing.terrain_park_breakdown.number_rails">
    <mso:type.object.description xml:lang="en">Property relating an mso:skiing.terrain_park_breakdown to the total number of rails in the mso:skiing.ski_area's terrain parks.</mso:type.object.description>
    <mso:type.object.name xml:lang="en">Number of Rails</mso:type.object.name>
    <mso:type.object.type rdf:resource="http://knowledge.microsoft.com/mso/type.property" />
    <mso:type.property.expected_type rdf:resource="http://knowledge.microsoft.com/mso/type.decimal" />
    <mso:type.property.max_cardinality rdf:datatype="http://www.w3.org/2001/XMLSchema#int">1</mso:type.property.max_cardinality>
    <mso:type.property.type rdf:resource="http://knowledge.microsoft.com/mso/skiing.terrain_park_breakdown" />
  </rdf:Description>
  <rdf:Description rdf:about="http://knowledge.microsoft.com/mso/skiing.terrain_park_breakdown.number_rails_open">
    <mso:type.object.description xml:lang="en">Property relating an mso:skiing.terrain_park_breakdown to the total number of rails open in the mso:skiing.ski_area's terrain parks.</mso:type.object.description>
    <mso:type.object.name xml:lang="en">Number of Open Rails</mso:type.object.name>
    <mso:type.object.type rdf:resource="http://knowledge.microsoft.com/mso/type.property" />
    <mso:type.property.expected_type rdf:resource="http://knowledge.microsoft.com/mso/type.decimal" />
    <mso:type.property.max_cardinality rdf:datatype="http://www.w3.org/2001/XMLSchema#int">1</mso:type.property.max_cardinality>
    <mso:type.property.type rdf:resource="http://knowledge.microsoft.com/mso/skiing.terrain_park_breakdown" />
  </rdf:Description>
  <rdf:Description rdf:about="http://knowledge.microsoft.com/mso/skiing.terrain_park_breakdown.open">
    <mso:type.object.description xml:lang="en">Property relating an mso:skiing.terrain_park_breakdown to the number of open terrain parks for mso:skiing.ski_area.</mso:type.object.description>
    <mso:type.object.name xml:lang="en">Open</mso:type.object.name>
    <mso:type.object.type rdf:resource="http://knowledge.microsoft.com/mso/type.property" />
    <mso:type.property.expected_type rdf:resource="http://knowledge.microsoft.com/mso/type.decimal" />
    <mso:type.property.max_cardinality rdf:datatype="http://www.w3.org/2001/XMLSchema#int">1</mso:type.property.max_cardinality>
    <mso:type.property.type rdf:resource="http://knowledge.microsoft.com/mso/skiing.terrain_park_breakdown" />
  </rdf:Description>
  <rdf:Description rdf:about="http://knowledge.microsoft.com/mso/skiing.yearly_snowfall">
    <mso:type.object.description xml:lang="en">Value type collecting the data for an mso:skiing.ski_area's yearly snowfall.</mso:type.object.description>
    <mso:type.object.name xml:lang="en">Yearly Snowfall</mso:type.object.name>
    <mso:type.object.type rdf:resource="http://knowledge.microsoft.com/mso/type.type" />
    <mso:type.type.category rdf:resource="http://knowledge.microsoft.com/mso/type.category.value_type" />
    <mso:type.type.domain rdf:resource="http://knowledge.microsoft.com/mso/skiing" />
    <mso:type.type.includes rdf:resource="http://knowledge.microsoft.com/mso/type.object" />
  </rdf:Description>
  <rdf:Description rdf:about="http://knowledge.microsoft.com/mso/skiing.yearly_snowfall.season_end">
    <mso:type.object.description xml:lang="en">Date of the end of the season.</mso:type.object.description>
    <mso:type.object.name xml:lang="en">Season end</mso:type.object.name>
    <mso:type.object.type rdf:resource="http://knowledge.microsoft.com/mso/type.property" />
    <mso:type.property.expected_type rdf:resource="http://knowledge.microsoft.com/mso/type.datetime" />
    <mso:type.property.max_cardinality rdf:datatype="http://www.w3.org/2001/XMLSchema#int">1</mso:type.property.max_cardinality>
    <mso:type.property.type rdf:resource="http://knowledge.microsoft.com/mso/skiing.yearly_snowfall" />
  </rdf:Description>
  <rdf:Description rdf:about="http://knowledge.microsoft.com/mso/skiing.yearly_snowfall.season_start">
    <mso:type.object.description xml:lang="en">Date of the start of the season.</mso:type.object.description>
    <mso:type.object.name xml:lang="en">Season start</mso:type.object.name>
    <mso:type.object.type rdf:resource="http://knowledge.microsoft.com/mso/type.property" />
    <mso:type.property.expected_type rdf:resource="http://knowledge.microsoft.com/mso/type.datetime" />
    <mso:type.property.max_cardinality rdf:datatype="http://www.w3.org/2001/XMLSchema#int">1</mso:type.property.max_cardinality>
    <mso:type.property.type rdf:resource="http://knowledge.microsoft.com/mso/skiing.yearly_snowfall" />
  </rdf:Description>
  <rdf:Description rdf:about="http://knowledge.microsoft.com/mso/skiing.yearly_snowfall.snowfall">
    <mso:type.object.description xml:lang="en">Yearly amount of snowfall (in centimeters).</mso:type.object.description>
    <mso:type.object.name xml:lang="en">Snowfall</mso:type.object.name>
    <mso:type.object.type rdf:resource="http://knowledge.microsoft.com/mso/type.property" />
    <mso:type.property.expected_type rdf:resource="http://knowledge.microsoft.com/mso/type.decimal" />
    <mso:type.property.max_cardinality rdf:datatype="http://www.w3.org/2001/XMLSchema#int">1</mso:type.property.max_cardinality>
    <mso:type.property.type rdf:resource="http://knowledge.microsoft.com/mso/skiing.yearly_snowfall" />
    <mso:type.property.unit rdf:resource="http://knowledge.microsoft.com/mso/type.unit.centimeter" />
  </rdf:Description>
</rdf:RDF>