<?xml version="1.0" encoding="utf-8"?>
<!--
!!!DO NOT EDIT. THIS FILE IS GENERATED BY CODE AND ANY CHANGES MAY BE OVERWRITTEN!!!
-->
<rdf:RDF xmlns:rdf="http://www.w3.org/1999/02/22-rdf-syntax-ns#" xmlns:kc="http://knowledge.microsoft.com/configuration/" xmlns:mso="http://knowledge.microsoft.com/mso/">
  <rdf:Description rdf:about="http://knowledge.microsoft.com/mso/type">
    <mso:type.domain.domain_group rdf:resource="http://knowledge.microsoft.com/domain_group/common" />
    <mso:type.object.name xml:lang="en">Type System</mso:type.object.name>
    <mso:type.object.type rdf:resource="http://knowledge.microsoft.com/mso/type.domain" />
  </rdf:Description>
  <rdf:Description rdf:about="http://knowledge.microsoft.com/mso/type.boolean">
    <mso:type.object.description xml:lang="en">The type for Boolean properties, viz. properties that have only two possible values.</mso:type.object.description>
    <mso:type.object.name xml:lang="en">Boolean</mso:type.object.name>
    <mso:type.object.type rdf:resource="http://knowledge.microsoft.com/mso/type.type" />
    <mso:type.type.category rdf:resource="http://knowledge.microsoft.com/mso/type.category.metadata" />
    <mso:type.type.domain rdf:resource="http://knowledge.microsoft.com/mso/type" />
    <mso:type.type.includes rdf:resource="http://knowledge.microsoft.com/mso/type.object" />
    <mso:type.type.includes rdf:resource="http://knowledge.microsoft.com/mso/type.value" />
  </rdf:Description>
  <rdf:Description rdf:about="http://knowledge.microsoft.com/mso/type.category">
    <mso:type.object.description xml:lang="en">An enumeration of the various categories of types, e.g. relationship, value type, abstract, primary entity, and enumeration.  Note that only the categories of relationship, primary entity, and enumeration are currently used in the ontology.</mso:type.object.description>
    <mso:type.object.name xml:lang="en">Type Category</mso:type.object.name>
    <mso:type.object.type rdf:resource="http://knowledge.microsoft.com/mso/type.type" />
    <mso:type.type.category rdf:resource="http://knowledge.microsoft.com/mso/type.category.metadata" />
    <mso:type.type.domain rdf:resource="http://knowledge.microsoft.com/mso/type" />
    <mso:type.type.includes rdf:resource="http://knowledge.microsoft.com/mso/type.object" />
  </rdf:Description>
  <rdf:Description rdf:about="http://knowledge.microsoft.com/mso/type.category.abstract">
    <mso:type.object.type rdf:resource="http://knowledge.microsoft.com/mso/type.category" />
  </rdf:Description>
  <rdf:Description rdf:about="http://knowledge.microsoft.com/mso/type.category.enumeration">
    <mso:type.object.type rdf:resource="http://knowledge.microsoft.com/mso/type.category" />
  </rdf:Description>
  <rdf:Description rdf:about="http://knowledge.microsoft.com/mso/type.category.metadata">
    <mso:type.object.type rdf:resource="http://knowledge.microsoft.com/mso/type.category" />
  </rdf:Description>
  <rdf:Description rdf:about="http://knowledge.microsoft.com/mso/type.category.primary_entity">
    <mso:type.object.type rdf:resource="http://knowledge.microsoft.com/mso/type.category" />
  </rdf:Description>
  <rdf:Description rdf:about="http://knowledge.microsoft.com/mso/type.category.relationship">
    <mso:type.object.type rdf:resource="http://knowledge.microsoft.com/mso/type.category" />
  </rdf:Description>
  <rdf:Description rdf:about="http://knowledge.microsoft.com/mso/type.category.value_type">
    <mso:type.object.type rdf:resource="http://knowledge.microsoft.com/mso/type.category" />
  </rdf:Description>
  <rdf:Description rdf:about="http://knowledge.microsoft.com/mso/type.conflation_hint">
    <mso:type.object.description xml:lang="en">Objects that are assigned this type are used in the conflation stage of the Satori pipeline.</mso:type.object.description>
    <mso:type.object.name xml:lang="en">Conflation Hint</mso:type.object.name>
    <mso:type.object.type rdf:resource="http://knowledge.microsoft.com/mso/type.type" />
    <mso:type.type.category rdf:resource="http://knowledge.microsoft.com/mso/type.category.metadata" />
    <mso:type.type.deprecation_info xml:lang="en">This type is not longer used in conflation. DeprecatedBy:[REDMOND\ianiles]</mso:type.type.deprecation_info>
    <mso:type.type.domain rdf:resource="http://knowledge.microsoft.com/mso/type" />
    <mso:type.type.includes rdf:resource="http://knowledge.microsoft.com/mso/type.object" />
  </rdf:Description>
  <rdf:Description rdf:about="http://knowledge.microsoft.com/mso/type.datetime">
    <mso:type.object.description xml:lang="en">Metadata representing date and time, as specific time points. It includes concepts like 'June 2013' and '7/10/1974 7:10:24 AM'.</mso:type.object.description>
    <mso:type.object.name xml:lang="en">Date/Time</mso:type.object.name>
    <mso:type.object.type rdf:resource="http://knowledge.microsoft.com/mso/type.type" />
    <mso:type.type.category rdf:resource="http://knowledge.microsoft.com/mso/type.category.metadata" />
    <mso:type.type.domain rdf:resource="http://knowledge.microsoft.com/mso/type" />
    <mso:type.type.includes rdf:resource="http://knowledge.microsoft.com/mso/type.object" />
    <mso:type.type.includes rdf:resource="http://knowledge.microsoft.com/mso/type.value" />
  </rdf:Description>
  <rdf:Description rdf:about="http://knowledge.microsoft.com/mso/type.decimal">
    <mso:type.object.description xml:lang="en">The type for literals that store numeric values.</mso:type.object.description>
    <mso:type.object.name xml:lang="en">Decimal Number</mso:type.object.name>
    <mso:type.object.type rdf:resource="http://knowledge.microsoft.com/mso/type.type" />
    <mso:type.type.category rdf:resource="http://knowledge.microsoft.com/mso/type.category.metadata" />
    <mso:type.type.domain rdf:resource="http://knowledge.microsoft.com/mso/type" />
    <mso:type.type.includes rdf:resource="http://knowledge.microsoft.com/mso/type.object" />
    <mso:type.type.includes rdf:resource="http://knowledge.microsoft.com/mso/type.value" />
  </rdf:Description>
  <rdf:Description rdf:about="http://knowledge.microsoft.com/mso/type.domain">
    <mso:type.object.description xml:lang="en">A grouping of types in the Satori Ontology, e.g. people, transportation, and tv.</mso:type.object.description>
    <mso:type.object.name xml:lang="en">Domain</mso:type.object.name>
    <mso:type.object.type rdf:resource="http://knowledge.microsoft.com/mso/type.type" />
    <mso:type.type.category rdf:resource="http://knowledge.microsoft.com/mso/type.category.metadata" />
    <mso:type.type.domain rdf:resource="http://knowledge.microsoft.com/mso/type" />
    <mso:type.type.includes rdf:resource="http://knowledge.microsoft.com/mso/type.object" />
  </rdf:Description>
  <rdf:Description rdf:about="http://knowledge.microsoft.com/mso/type.domain.domain_group">
    <mso:type.object.description xml:lang="en">A property that relates a domain to its corresponding domain group, e.g. the Spaceflight domain is related to the Science domain group.</mso:type.object.description>
    <mso:type.object.name xml:lang="en">Domain Group</mso:type.object.name>
    <mso:type.object.type rdf:resource="http://knowledge.microsoft.com/mso/type.property" />
    <mso:type.property.expected_type rdf:resource="http://knowledge.microsoft.com/mso/type.domain_group" />
    <mso:type.property.type rdf:resource="http://knowledge.microsoft.com/mso/type.domain" />
  </rdf:Description>
  <rdf:Description rdf:about="http://knowledge.microsoft.com/mso/type.domain_group">
    <mso:type.object.description xml:lang="en">A grouping of related domains.  Although most domains in Satori are assigned a domain group, domain groups are currently not shown to the user.</mso:type.object.description>
    <mso:type.object.name xml:lang="en">Domain Group</mso:type.object.name>
    <mso:type.object.type rdf:resource="http://knowledge.microsoft.com/mso/type.type" />
    <mso:type.type.category rdf:resource="http://knowledge.microsoft.com/mso/type.category.metadata" />
    <mso:type.type.domain rdf:resource="http://knowledge.microsoft.com/mso/type" />
    <mso:type.type.includes rdf:resource="http://knowledge.microsoft.com/mso/type.object" />
  </rdf:Description>
  <rdf:Description rdf:about="http://knowledge.microsoft.com/mso/type.key">
    <mso:type.object.description xml:lang="en">An internal or external identifier for an element of the Satori Ontology</mso:type.object.description>
    <mso:type.object.name xml:lang="en">Key</mso:type.object.name>
    <mso:type.object.type rdf:resource="http://knowledge.microsoft.com/mso/type.type" />
    <mso:type.type.category rdf:resource="http://knowledge.microsoft.com/mso/type.category.metadata" />
    <mso:type.type.domain rdf:resource="http://knowledge.microsoft.com/mso/type" />
    <mso:type.type.includes rdf:resource="http://knowledge.microsoft.com/mso/type.object" />
  </rdf:Description>
  <rdf:Description rdf:about="http://knowledge.microsoft.com/mso/type.key.hash">
    <mso:type.object.description xml:lang="en">A property that relates an internal or external identifier to the corresponding object in Satori.</mso:type.object.description>
    <mso:type.object.name xml:lang="en">Hash</mso:type.object.name>
    <mso:type.object.type rdf:resource="http://knowledge.microsoft.com/mso/type.property" />
    <mso:type.property.expected_type rdf:resource="http://knowledge.microsoft.com/mso/type.object" />
    <mso:type.property.max_cardinality rdf:datatype="http://www.w3.org/2001/XMLSchema#int">1</mso:type.property.max_cardinality>
    <mso:type.property.min_cardinality rdf:datatype="http://www.w3.org/2001/XMLSchema#int">1</mso:type.property.min_cardinality>
    <mso:type.property.type rdf:resource="http://knowledge.microsoft.com/mso/type.key" />
  </rdf:Description>
  <rdf:Description rdf:about="http://knowledge.microsoft.com/mso/type.key.name">
    <mso:type.object.name xml:lang="en">name</mso:type.object.name>
    <mso:type.object.type rdf:resource="http://knowledge.microsoft.com/mso/type.property" />
    <mso:type.property.deprecation_info xml:lang="en">Use type.object.name instead. DeprecatedBy:[ianiles] Successor:[mso:type.object.name]</mso:type.property.deprecation_info>
    <mso:type.property.expected_type rdf:resource="http://knowledge.microsoft.com/mso/type.string" />
    <mso:type.property.max_cardinality rdf:datatype="http://www.w3.org/2001/XMLSchema#int">1</mso:type.property.max_cardinality>
    <mso:type.property.min_cardinality rdf:datatype="http://www.w3.org/2001/XMLSchema#int">1</mso:type.property.min_cardinality>
    <mso:type.property.type rdf:resource="http://knowledge.microsoft.com/mso/type.key" />
  </rdf:Description>
  <rdf:Description rdf:about="http://knowledge.microsoft.com/mso/type.key.namespace">
    <mso:type.object.description xml:lang="en">The part of the key before the ":" that indicates the data source, e.g. "fb:", which stands for Freebase.</mso:type.object.description>
    <mso:type.object.name xml:lang="en">Namespace</mso:type.object.name>
    <mso:type.object.type rdf:resource="http://knowledge.microsoft.com/mso/type.property" />
    <mso:type.property.expected_type rdf:resource="http://knowledge.microsoft.com/mso/type.namespace" />
    <mso:type.property.max_cardinality rdf:datatype="http://www.w3.org/2001/XMLSchema#int">1</mso:type.property.max_cardinality>
    <mso:type.property.min_cardinality rdf:datatype="http://www.w3.org/2001/XMLSchema#int">1</mso:type.property.min_cardinality>
    <mso:type.property.type rdf:resource="http://knowledge.microsoft.com/mso/type.key" />
  </rdf:Description>
  <rdf:Description rdf:about="http://knowledge.microsoft.com/mso/type.namespace">
    <mso:type.object.description xml:lang="en">The type for all namespaces, including namespaces for the Satori Ontology ("mso:"), as well as namespaces for type.object.key and type.object.subject_key (e.g. "fb:").</mso:type.object.description>
    <mso:type.object.name xml:lang="en">Namespace</mso:type.object.name>
    <mso:type.object.type rdf:resource="http://knowledge.microsoft.com/mso/type.type" />
    <mso:type.type.category rdf:resource="http://knowledge.microsoft.com/mso/type.category.metadata" />
    <mso:type.type.domain rdf:resource="http://knowledge.microsoft.com/mso/type" />
    <mso:type.type.includes rdf:resource="http://knowledge.microsoft.com/mso/type.object" />
  </rdf:Description>
  <rdf:Description rdf:about="http://knowledge.microsoft.com/mso/type.object">
    <mso:type.object.description xml:lang="en">the most basic type in the system. This type contains all of the elements of the ontology, whether types, properties or entities.</mso:type.object.description>
    <mso:type.object.name xml:lang="en">Object</mso:type.object.name>
    <mso:type.object.type rdf:resource="http://knowledge.microsoft.com/mso/type.type" />
    <mso:type.type.category rdf:resource="http://knowledge.microsoft.com/mso/type.category.abstract" />
    <mso:type.type.domain rdf:resource="http://knowledge.microsoft.com/mso/type" />
  </rdf:Description>
  <rdf:Description rdf:about="http://knowledge.microsoft.com/mso/type.object.abbreviation">
    <mso:type.object.description xml:lang="en">An abbreviated form of a name of the object.  For example, the short name of Microsoft Office 2012 is Office 2012, the short name of the People's Republic of China is China, and the short name of the Metropolitan Atlanta Rapid Transit Authority is MARTA.</mso:type.object.description>
    <mso:type.object.name xml:lang="en">Short Name</mso:type.object.name>
    <mso:type.object.type rdf:resource="http://knowledge.microsoft.com/mso/type.property" />
    <mso:type.property.expected_type rdf:resource="http://knowledge.microsoft.com/mso/type.text" />
    <mso:type.property.type rdf:resource="http://knowledge.microsoft.com/mso/type.object" />
  </rdf:Description>
  <rdf:Description rdf:about="http://knowledge.microsoft.com/mso/type.object.adult_score">
    <mso:type.object.description xml:lang="en">A value from 0 to 1 indicating the amount of adult content of the object.  A score of 0 means that the object has no adult content.</mso:type.object.description>
    <mso:type.object.name xml:lang="en">Adult Score</mso:type.object.name>
    <mso:type.object.type rdf:resource="http://knowledge.microsoft.com/mso/type.property" />
    <mso:type.property.expected_type rdf:resource="http://knowledge.microsoft.com/mso/type.decimal" />
    <mso:type.property.max_cardinality rdf:datatype="http://www.w3.org/2001/XMLSchema#int">1</mso:type.property.max_cardinality>
    <mso:type.property.type rdf:resource="http://knowledge.microsoft.com/mso/type.object" />
  </rdf:Description>
  <rdf:Description rdf:about="http://knowledge.microsoft.com/mso/type.object.alias">
    <mso:type.object.alias xml:lang="en">Also Known As</mso:type.object.alias>
    <mso:type.object.alias xml:lang="en">Synonym</mso:type.object.alias>
    <mso:type.object.description xml:lang="en">An alternate name for the given object.  Note that this property generally contains terms that would *not* be shown to a user, e.g. misspellings, ambiguous expressions, noncanonical phrases, etc.</mso:type.object.description>
    <mso:type.object.name xml:lang="en">Alias</mso:type.object.name>
    <mso:type.object.type rdf:resource="http://knowledge.microsoft.com/mso/type.property" />
    <mso:type.property.expected_type rdf:resource="http://knowledge.microsoft.com/mso/type.text" />
    <mso:type.property.type rdf:resource="http://knowledge.microsoft.com/mso/type.object" />
  </rdf:Description>
  <rdf:Description rdf:about="http://knowledge.microsoft.com/mso/type.object.annotated_description">
    <mso:type.object.description xml:lang="en">A description that contains markup, e.g. HTML or XML.</mso:type.object.description>
    <mso:type.object.name xml:lang="en">Annotated Description</mso:type.object.name>
    <mso:type.object.type rdf:resource="http://knowledge.microsoft.com/mso/type.property" />
    <mso:type.property.expected_type rdf:resource="http://knowledge.microsoft.com/mso/type.text" />
    <mso:type.property.type rdf:resource="http://knowledge.microsoft.com/mso/type.object" />
  </rdf:Description>
  <rdf:Description rdf:about="http://knowledge.microsoft.com/mso/type.object.attribution">
    <mso:type.object.description xml:lang="en">A property that points to information about a data provider of the given object.</mso:type.object.description>
    <mso:type.object.name xml:lang="en">attribution</mso:type.object.name>
    <mso:type.object.type rdf:resource="http://knowledge.microsoft.com/mso/type.property" />
    <mso:type.property.expected_type rdf:resource="http://knowledge.microsoft.com/mso/common.attribution" />
    <mso:type.property.type rdf:resource="http://knowledge.microsoft.com/mso/type.object" />
  </rdf:Description>
  <rdf:Description rdf:about="http://knowledge.microsoft.com/mso/type.object.best_key">
    <mso:type.object.description xml:lang="en">The preferred identifier for the object in a particular namespace, e.g. Satori, Facebook, Wikipedia, etc.</mso:type.object.description>
    <mso:type.object.name xml:lang="en">Best Key</mso:type.object.name>
    <mso:type.object.type rdf:resource="http://knowledge.microsoft.com/mso/type.property" />
    <mso:type.property.expected_type rdf:resource="http://knowledge.microsoft.com/mso/type.key" />
    <mso:type.property.type rdf:resource="http://knowledge.microsoft.com/mso/type.object" />
  </rdf:Description>
  <rdf:Description rdf:about="http://knowledge.microsoft.com/mso/type.object.brief_description">
    <mso:type.object.description xml:lang="en">A property that relates an object to a concise or shortened form of a corresponding description.</mso:type.object.description>
    <mso:type.object.name xml:lang="en">Brief Description</mso:type.object.name>
    <mso:type.object.type rdf:resource="http://knowledge.microsoft.com/mso/type.property" />
    <mso:type.property.expected_type rdf:resource="http://knowledge.microsoft.com/mso/type.text" />
    <mso:type.property.type rdf:resource="http://knowledge.microsoft.com/mso/type.object" />
  </rdf:Description>
  <rdf:Description rdf:about="http://knowledge.microsoft.com/mso/type.object.composite_image">
    <mso:type.object.description xml:lang="en">The panoramas or photosynths to display for this entity.</mso:type.object.description>
    <mso:type.object.name xml:lang="en">Composite Image</mso:type.object.name>
    <mso:type.object.type rdf:resource="http://knowledge.microsoft.com/mso/type.property" />
    <mso:type.property.deprecation_info xml:lang="en">Use type.object.image and common.image.label to indicate that an image is a "composite image". DeprecatedBy:[REDMOND\ianiles] Successor:[mso:type.object.image]</mso:type.property.deprecation_info>
    <mso:type.property.expected_type rdf:resource="http://knowledge.microsoft.com/mso/common.composite_image" />
    <mso:type.property.type rdf:resource="http://knowledge.microsoft.com/mso/type.object" />
  </rdf:Description>
  <rdf:Description rdf:about="http://knowledge.microsoft.com/mso/type.object.coreference">
    <mso:type.object.description xml:lang="en">A virtual property that links an entity to another entity, when both are the subject of a particular text passage.</mso:type.object.description>
    <mso:type.object.name xml:lang="en">Coreferenced Entities</mso:type.object.name>
    <mso:type.object.type rdf:resource="http://knowledge.microsoft.com/mso/type.property" />
    <mso:type.object.type rdf:resource="http://knowledge.microsoft.com/mso/type.virtual_property" />
    <mso:type.property.deprecation_info xml:lang="en">Use textPassage:type.object.coreferenced_entity instead. DeprecatedBy:[REDMOND\sunkumar] Successor:[textPassage:type.object.coreferenced_entity]</mso:type.property.deprecation_info>
    <mso:type.property.expected_type rdf:resource="http://knowledge.microsoft.com/mso/type.object" />
    <mso:type.property.type rdf:resource="http://knowledge.microsoft.com/mso/type.object" />
  </rdf:Description>
  <rdf:Description rdf:about="http://knowledge.microsoft.com/mso/type.object.current">
    <mso:type.object.description xml:lang="en">A Boolean property that indicates whether the object exists or is of interest/importance at the present time, e.g. that a position is held.  Note that the values of this property should be set as follows:  
type.object.current = 1: the object is of interest/importance at the present time.
type.object.current = 0: the object was of interest/importance before the present time.  In cases of future or unknown interest/importance, the property should not be set.
 </mso:type.object.description>
    <mso:type.object.name xml:lang="en">Current</mso:type.object.name>
    <mso:type.object.type rdf:resource="http://knowledge.microsoft.com/mso/type.property" />
    <mso:type.property.expected_type rdf:resource="http://knowledge.microsoft.com/mso/type.boolean" />
    <mso:type.property.max_cardinality rdf:datatype="http://www.w3.org/2001/XMLSchema#int">1</mso:type.property.max_cardinality>
    <mso:type.property.type rdf:resource="http://knowledge.microsoft.com/mso/type.object" />
  </rdf:Description>
  <rdf:Description rdf:about="http://knowledge.microsoft.com/mso/type.object.description">
    <mso:type.object.description xml:lang="en">Text in the form of a definition or an exposition that specifies the most salient characteristics of the given entity.</mso:type.object.description>
    <mso:type.object.name xml:lang="en">Description</mso:type.object.name>
    <mso:type.object.type rdf:resource="http://knowledge.microsoft.com/mso/type.property" />
    <mso:type.property.expected_type rdf:resource="http://knowledge.microsoft.com/mso/type.text" />
    <mso:type.property.type rdf:resource="http://knowledge.microsoft.com/mso/type.object" />
  </rdf:Description>
  <rdf:Description rdf:about="http://knowledge.microsoft.com/mso/type.object.dominant_type">
    <mso:type.object.description xml:lang="en">A property relating an entity to the most significant type(s) corresponding to the entity.  For example, this property relates the Tom Hanks entity to the types mso:film.actor and mso:celebrities.celebrity.</mso:type.object.description>
    <mso:type.object.name xml:lang="en">Dominant Type</mso:type.object.name>
    <mso:type.object.type rdf:resource="http://knowledge.microsoft.com/mso/type.property" />
    <mso:type.property.expected_type rdf:resource="http://knowledge.microsoft.com/mso/type.type" />
    <mso:type.property.type rdf:resource="http://knowledge.microsoft.com/mso/type.object" />
  </rdf:Description>
  <rdf:Description rdf:about="http://knowledge.microsoft.com/mso/type.object.editorial_record">
    <mso:type.object.description xml:lang="en">A property that relates an entity to information about editorial updates that were made to the entity.</mso:type.object.description>
    <mso:type.object.name xml:lang="en">Editorial Record</mso:type.object.name>
    <mso:type.object.type rdf:resource="http://knowledge.microsoft.com/mso/type.property" />
    <mso:type.property.expected_type rdf:resource="http://knowledge.microsoft.com/mso/common.editorial_record" />
    <mso:type.property.type rdf:resource="http://knowledge.microsoft.com/mso/type.object" />
  </rdf:Description>
  <rdf:Description rdf:about="http://knowledge.microsoft.com/mso/type.object.etymology">
    <mso:type.object.description xml:lang="en">A property that relates an object to the etymology of the preferred name for the object.</mso:type.object.description>
    <mso:type.object.name xml:lang="en">Etymology</mso:type.object.name>
    <mso:type.object.type rdf:resource="http://knowledge.microsoft.com/mso/type.property" />
    <mso:type.property.expected_type rdf:resource="http://knowledge.microsoft.com/mso/type.text" />
    <mso:type.property.type rdf:resource="http://knowledge.microsoft.com/mso/type.object" />
  </rdf:Description>
  <rdf:Description rdf:about="http://knowledge.microsoft.com/mso/type.object.former_name">
    <mso:type.object.description xml:lang="en">A previous name for the object.  Note that in, cases where an object has changed its name once and only once, the values for type.object.former_name and type.object.original_name will be the same.  Otherwise, they may differ. </mso:type.object.description>
    <mso:type.object.name xml:lang="en">former name</mso:type.object.name>
    <mso:type.object.type rdf:resource="http://knowledge.microsoft.com/mso/type.property" />
    <mso:type.property.expected_type rdf:resource="http://knowledge.microsoft.com/mso/type.text" />
    <mso:type.property.type rdf:resource="http://knowledge.microsoft.com/mso/type.object" />
  </rdf:Description>
  <rdf:Description rdf:about="http://knowledge.microsoft.com/mso/type.object.image">
    <mso:type.object.description xml:lang="en">A property relating objects to their images. For historical reasons, type.object.preferred_image is semtantically identical with this field and should be preferred.</mso:type.object.description>
    <mso:type.object.name xml:lang="en">image</mso:type.object.name>
    <mso:type.object.type rdf:resource="http://knowledge.microsoft.com/mso/type.property" />
    <mso:type.property.expected_type rdf:resource="http://knowledge.microsoft.com/mso/common.image" />
    <mso:type.property.type rdf:resource="http://knowledge.microsoft.com/mso/type.object" />
  </rdf:Description>
  <rdf:Description rdf:about="http://knowledge.microsoft.com/mso/type.object.key">
    <mso:type.object.description xml:lang="en">A property that links an object to a global identifier (i.e. an identifier that is independent of all of the sources from which information about the object is extracted) for the object in a particular namespace, e.g. Satori, Facebook, Wikipedia, etc.</mso:type.object.description>
    <mso:type.object.name xml:lang="en">Key</mso:type.object.name>
    <mso:type.object.type rdf:resource="http://knowledge.microsoft.com/mso/type.property" />
    <mso:type.property.expected_type rdf:resource="http://knowledge.microsoft.com/mso/type.key" />
    <mso:type.property.type rdf:resource="http://knowledge.microsoft.com/mso/type.object" />
  </rdf:Description>
  <rdf:Description rdf:about="http://knowledge.microsoft.com/mso/type.object.keyword">
    <mso:type.object.description xml:lang="en">A keyword, i.e. a search query or a search query term, associated with the entity.</mso:type.object.description>
    <mso:type.object.name xml:lang="en">Keyword</mso:type.object.name>
    <mso:type.object.type rdf:resource="http://knowledge.microsoft.com/mso/type.property" />
    <mso:type.property.expected_type rdf:resource="http://knowledge.microsoft.com/mso/common.keyword" />
    <mso:type.property.type rdf:resource="http://knowledge.microsoft.com/mso/type.object" />
  </rdf:Description>
  <rdf:Description rdf:about="http://knowledge.microsoft.com/mso/type.object.locale">
    <mso:type.object.name xml:lang="en">Locale</mso:type.object.name>
    <mso:type.object.type rdf:resource="http://knowledge.microsoft.com/mso/type.property" />
    <mso:type.property.deprecation_info xml:lang="en">It's not clear what the intended meaning of this property is. DeprecatedBy:[REDMOND\ianiles]</mso:type.property.deprecation_info>
    <mso:type.property.expected_type rdf:resource="http://knowledge.microsoft.com/mso/type.string" />
    <mso:type.property.type rdf:resource="http://knowledge.microsoft.com/mso/type.object" />
  </rdf:Description>
  <rdf:Description rdf:about="http://knowledge.microsoft.com/mso/type.object.localization">
    <mso:type.object.description xml:lang="en">A property that relates an entity to information about the translation of a name of the entity into another language/dialect.</mso:type.object.description>
    <mso:type.object.name xml:lang="en">Localization</mso:type.object.name>
    <mso:type.object.type rdf:resource="http://knowledge.microsoft.com/mso/type.property" />
    <mso:type.object.type rdf:resource="http://knowledge.microsoft.com/mso/type.virtual_property" />
    <mso:type.property.expected_type rdf:resource="http://knowledge.microsoft.com/mso/common.localization" />
    <mso:type.property.inverse_of rdf:resource="mso:common.localization.object" />
    <mso:type.property.type rdf:resource="http://knowledge.microsoft.com/mso/type.object" />
  </rdf:Description>
  <rdf:Description rdf:about="http://knowledge.microsoft.com/mso/type.object.mention_url">
    <mso:type.object.name xml:lang="en">Mention Url</mso:type.object.name>
    <mso:type.object.type rdf:resource="http://knowledge.microsoft.com/mso/type.property" />
    <mso:type.property.deprecation_info xml:lang="en">It's not clear what the intended meaning of this property is. DeprecatedBy:[REDMOND\ianiles]</mso:type.property.deprecation_info>
    <mso:type.property.expected_type rdf:resource="http://knowledge.microsoft.com/mso/type.uri" />
    <mso:type.property.type rdf:resource="http://knowledge.microsoft.com/mso/type.object" />
  </rdf:Description>
  <rdf:Description rdf:about="http://knowledge.microsoft.com/mso/type.object.name">
    <mso:type.object.description xml:lang="en">A word or phrase which refers to the object.  Note that this field should contain only terms that can be displayed to a user.</mso:type.object.description>
    <mso:type.object.name xml:lang="en">Name</mso:type.object.name>
    <mso:type.object.type rdf:resource="http://knowledge.microsoft.com/mso/type.property" />
    <mso:type.property.expected_type rdf:resource="http://knowledge.microsoft.com/mso/type.text" />
    <mso:type.property.type rdf:resource="http://knowledge.microsoft.com/mso/type.object" />
  </rdf:Description>
  <rdf:Description rdf:about="http://knowledge.microsoft.com/mso/type.object.nickname">
    <mso:type.object.description xml:lang="en">An affectionate name, usually based on a salient characteristic of the thing named, e.g. the nickname of John F. Kennedy was "Jack" and two nicknames of the city of Seattle are the "Emerald City" and the "Jet City".</mso:type.object.description>
    <mso:type.object.name xml:lang="en">Nickname</mso:type.object.name>
    <mso:type.object.type rdf:resource="http://knowledge.microsoft.com/mso/type.property" />
    <mso:type.property.expected_type rdf:resource="http://knowledge.microsoft.com/mso/type.text" />
    <mso:type.property.type rdf:resource="http://knowledge.microsoft.com/mso/type.object" />
  </rdf:Description>
  <rdf:Description rdf:about="http://knowledge.microsoft.com/mso/type.object.nonconflatable">
    <mso:type.object.description xml:lang="en">A Boolean property that indicates that the corresponding entity should not be conflated with other entities when this property is set to 1.  When this property is not set (the default option) or is set to 0, the corresponding entity can be conflated with other entities.  </mso:type.object.description>
    <mso:type.object.name xml:lang="en">Nonconflatable</mso:type.object.name>
    <mso:type.object.type rdf:resource="http://knowledge.microsoft.com/mso/type.property" />
    <mso:type.property.expected_type rdf:resource="http://knowledge.microsoft.com/mso/type.boolean" />
    <mso:type.property.max_cardinality rdf:datatype="http://www.w3.org/2001/XMLSchema#int">1</mso:type.property.max_cardinality>
    <mso:type.property.type rdf:resource="http://knowledge.microsoft.com/mso/type.object" />
  </rdf:Description>
  <rdf:Description rdf:about="http://knowledge.microsoft.com/mso/type.object.official_name">
    <mso:type.object.description xml:lang="en">The legal, formal, or full name for the object.  For objects that that still exist (e.g. living people, existing countries), this will be the current official name.  For objects that no longer exist, this will be the official name that the object had at the time of its demise (e.g. deceased people, former countries).</mso:type.object.description>
    <mso:type.object.name xml:lang="en">Official Name</mso:type.object.name>
    <mso:type.object.type rdf:resource="http://knowledge.microsoft.com/mso/type.property" />
    <mso:type.property.expected_type rdf:resource="http://knowledge.microsoft.com/mso/type.text" />
    <mso:type.property.type rdf:resource="http://knowledge.microsoft.com/mso/type.object" />
  </rdf:Description>
  <rdf:Description rdf:about="http://knowledge.microsoft.com/mso/type.object.original_name">
    <mso:type.object.description xml:lang="en">The name that the object had before any others, e.g. maiden name or the title of a movie when it was first released.</mso:type.object.description>
    <mso:type.object.name xml:lang="en">original name</mso:type.object.name>
    <mso:type.object.type rdf:resource="http://knowledge.microsoft.com/mso/type.property" />
    <mso:type.property.expected_type rdf:resource="http://knowledge.microsoft.com/mso/type.text" />
    <mso:type.property.max_cardinality rdf:datatype="http://www.w3.org/2001/XMLSchema#int">1</mso:type.property.max_cardinality>
    <mso:type.property.type rdf:resource="http://knowledge.microsoft.com/mso/type.object" />
  </rdf:Description>
  <rdf:Description rdf:about="http://knowledge.microsoft.com/mso/type.object.perceived_identical_entity">
    <mso:type.object.description xml:lang="en">Property relating an mso:type.object to another mso:type.object in which the entities are so closely related to be considered inter-changeable. An example is Amazon.com, Inc, the company, and amazon.com, the website. This property is based on an experimental property directly ingested from freebase.</mso:type.object.description>
    <mso:type.object.name xml:lang="en">Perceived Idential Entity</mso:type.object.name>
    <mso:type.object.type rdf:resource="http://knowledge.microsoft.com/mso/type.property" />
    <mso:type.property.expected_type rdf:resource="http://knowledge.microsoft.com/mso/type.object" />
    <mso:type.property.type rdf:resource="http://knowledge.microsoft.com/mso/type.object" />
  </rdf:Description>
  <rdf:Description rdf:about="http://knowledge.microsoft.com/mso/type.object.popularity">
    <mso:type.object.description xml:lang="en">Virtual property relating an entity to the mso:common.popularity relationship collecting data about the entity's popularity.</mso:type.object.description>
    <mso:type.object.name xml:lang="en">Popularity</mso:type.object.name>
    <mso:type.object.type rdf:resource="http://knowledge.microsoft.com/mso/type.property" />
    <mso:type.object.type rdf:resource="http://knowledge.microsoft.com/mso/type.virtual_property" />
    <mso:type.property.expected_type rdf:resource="http://knowledge.microsoft.com/mso/common.popularity" />
    <mso:type.property.inverse_of rdf:resource="mso:common.popularity.popular_item" />
    <mso:type.property.type rdf:resource="http://knowledge.microsoft.com/mso/type.object" />
  </rdf:Description>
  <rdf:Description rdf:about="http://knowledge.microsoft.com/mso/type.object.preferred_annotated_description">
    <mso:type.object.description xml:lang="en">The type.object.annotated_description that is regarded as the best one.  The property type.object.annotated_description should be used for ingested sources, and the best descriptions will be promoted later to type.object.preferred_annotated_description.</mso:type.object.description>
    <mso:type.object.name xml:lang="en">Preferred Annotated Description</mso:type.object.name>
    <mso:type.object.type rdf:resource="http://knowledge.microsoft.com/mso/type.property" />
    <mso:type.property.expected_type rdf:resource="http://knowledge.microsoft.com/mso/type.text" />
    <mso:type.property.max_cardinality rdf:datatype="http://www.w3.org/2001/XMLSchema#int">1</mso:type.property.max_cardinality>
    <mso:type.property.type rdf:resource="http://knowledge.microsoft.com/mso/type.object" />
  </rdf:Description>
  <rdf:Description rdf:about="http://knowledge.microsoft.com/mso/type.object.preferred_description">
    <mso:type.object.description xml:lang="en">The type.object.description that is regarded as the best one.  The property type.object.description should be used for ingested sources, and the best descriptions will be promoted later to type.object.preferred_description.</mso:type.object.description>
    <mso:type.object.name xml:lang="en">Preferred Description</mso:type.object.name>
    <mso:type.object.type rdf:resource="http://knowledge.microsoft.com/mso/type.property" />
    <mso:type.property.expected_type rdf:resource="http://knowledge.microsoft.com/mso/type.text" />
    <mso:type.property.max_cardinality rdf:datatype="http://www.w3.org/2001/XMLSchema#int">1</mso:type.property.max_cardinality>
    <mso:type.property.type rdf:resource="http://knowledge.microsoft.com/mso/type.object" />
  </rdf:Description>
  <rdf:Description rdf:about="http://knowledge.microsoft.com/mso/type.object.preferred_image">
    <mso:type.object.description xml:lang="en">A property relating an object to its best image(s).  Note that the value for type.object.preferred_image should also be a value of type.object.image.</mso:type.object.description>
    <mso:type.object.name xml:lang="en">Preferred Image</mso:type.object.name>
    <mso:type.object.type rdf:resource="http://knowledge.microsoft.com/mso/type.property" />
    <mso:type.property.expected_type rdf:resource="http://knowledge.microsoft.com/mso/common.image" />
    <mso:type.property.type rdf:resource="http://knowledge.microsoft.com/mso/type.object" />
  </rdf:Description>
  <rdf:Description rdf:about="http://knowledge.microsoft.com/mso/type.object.preferred_name">
    <mso:type.object.description xml:lang="en">The name of the object that is best for display purposes.  Note that the value of type.object.preferred_name for a given object should also be a value of type.object.name</mso:type.object.description>
    <mso:type.object.name xml:lang="en">Preferred Name</mso:type.object.name>
    <mso:type.object.type rdf:resource="http://knowledge.microsoft.com/mso/type.property" />
    <mso:type.property.expected_type rdf:resource="http://knowledge.microsoft.com/mso/type.text" />
    <mso:type.property.max_cardinality rdf:datatype="http://www.w3.org/2001/XMLSchema#int">1</mso:type.property.max_cardinality>
    <mso:type.property.type rdf:resource="http://knowledge.microsoft.com/mso/type.object" />
  </rdf:Description>
  <rdf:Description rdf:about="http://knowledge.microsoft.com/mso/type.object.ranking">
    <mso:type.object.description xml:lang="en">A property that links an object to information about the ranking of the object.</mso:type.object.description>
    <mso:type.object.name xml:lang="en">Object Ranking</mso:type.object.name>
    <mso:type.object.type rdf:resource="http://knowledge.microsoft.com/mso/type.property" />
    <mso:type.property.expected_type rdf:resource="http://knowledge.microsoft.com/mso/common.entity_ranking" />
    <mso:type.property.max_cardinality rdf:datatype="http://www.w3.org/2001/XMLSchema#int">1</mso:type.property.max_cardinality>
    <mso:type.property.type rdf:resource="http://knowledge.microsoft.com/mso/type.object" />
  </rdf:Description>
  <rdf:Description rdf:about="http://knowledge.microsoft.com/mso/type.object.redirect">
    <mso:type.object.name xml:lang="en">redirect</mso:type.object.name>
    <mso:type.object.type rdf:resource="http://knowledge.microsoft.com/mso/type.property" />
    <mso:type.property.deprecation_info xml:lang="en">It's not clear what the intended meaning of this property is. DeprecatedBy:[REDMOND\ianiles]</mso:type.property.deprecation_info>
    <mso:type.property.expected_type rdf:resource="http://knowledge.microsoft.com/mso/type.object" />
    <mso:type.property.max_cardinality rdf:datatype="http://www.w3.org/2001/XMLSchema#int">1</mso:type.property.max_cardinality>
    <mso:type.property.type rdf:resource="http://knowledge.microsoft.com/mso/type.object" />
  </rdf:Description>
  <rdf:Description rdf:about="http://knowledge.microsoft.com/mso/type.object.related_concept">
    <mso:type.object.description xml:lang="en">A property that relates an object (type, property or entity) to a node in an external schema.</mso:type.object.description>
    <mso:type.object.name xml:lang="en">Related Concept</mso:type.object.name>
    <mso:type.object.type rdf:resource="http://knowledge.microsoft.com/mso/type.property" />
    <mso:type.object.type rdf:resource="http://knowledge.microsoft.com/mso/type.virtual_property" />
    <mso:type.property.deprecation_info xml:lang="en">Use type.object.related_object_external instead. DeprecatedBy:[REDMOND\ianiles] Successor:[mso:type.object.related_object_external]</mso:type.property.deprecation_info>
    <mso:type.property.expected_type rdf:resource="http://knowledge.microsoft.com/mso/type.string" />
    <mso:type.property.type rdf:resource="http://knowledge.microsoft.com/mso/type.object" />
  </rdf:Description>
  <rdf:Description rdf:about="http://knowledge.microsoft.com/mso/type.object.related_object">
    <mso:type.object.description xml:lang="en">A property that relates an object in the ontology (a type, property or entity) with information about a similar object in the ontology.</mso:type.object.description>
    <mso:type.object.name xml:lang="en">Related Object</mso:type.object.name>
    <mso:type.object.type rdf:resource="http://knowledge.microsoft.com/mso/type.property" />
    <mso:type.property.expected_type rdf:resource="http://knowledge.microsoft.com/mso/common.related_internal_concept" />
    <mso:type.property.inverse_of rdf:resource="mso:common.related_internal_concept.subject_object" />
    <mso:type.property.type rdf:resource="http://knowledge.microsoft.com/mso/type.object" />
  </rdf:Description>
  <rdf:Description rdf:about="http://knowledge.microsoft.com/mso/type.object.related_object_external">
    <mso:type.object.description xml:lang="en">A virtual property that relates an object (type, property or entity) to information about its relationship to a node in an external schema.</mso:type.object.description>
    <mso:type.object.name xml:lang="en">Related External Object</mso:type.object.name>
    <mso:type.object.type rdf:resource="http://knowledge.microsoft.com/mso/type.property" />
    <mso:type.object.type rdf:resource="http://knowledge.microsoft.com/mso/type.virtual_property" />
    <mso:type.property.expected_type rdf:resource="http://knowledge.microsoft.com/mso/common.related_external_concept" />
    <mso:type.property.inverse_of rdf:resource="mso:common.related_external_concept.object " />
    <mso:type.property.type rdf:resource="http://knowledge.microsoft.com/mso/type.object" />
  </rdf:Description>
  <rdf:Description rdf:about="http://knowledge.microsoft.com/mso/type.object.representative_source_url">
    <mso:type.object.description xml:lang="en">A property that relates an object to a limited set of source URLs that are considered to be representative for the object.</mso:type.object.description>
    <mso:type.object.name xml:lang="en">Representative Source URL</mso:type.object.name>
    <mso:type.object.type rdf:resource="http://knowledge.microsoft.com/mso/type.property" />
    <mso:type.property.expected_type rdf:resource="http://knowledge.microsoft.com/mso/type.uri" />
    <mso:type.property.type rdf:resource="http://knowledge.microsoft.com/mso/type.object" />
  </rdf:Description>
  <rdf:Description rdf:about="http://knowledge.microsoft.com/mso/type.object.source_url">
    <mso:type.object.description xml:lang="en">A property that links an object to URLs that provide data for the object.</mso:type.object.description>
    <mso:type.object.name xml:lang="en">Source URL</mso:type.object.name>
    <mso:type.object.type rdf:resource="http://knowledge.microsoft.com/mso/type.property" />
    <mso:type.property.expected_type rdf:resource="http://knowledge.microsoft.com/mso/type.uri" />
    <mso:type.property.type rdf:resource="http://knowledge.microsoft.com/mso/type.object" />
  </rdf:Description>
  <rdf:Description rdf:about="http://knowledge.microsoft.com/mso/type.object.subject_key">
    <mso:type.object.description xml:lang="en">A property that links an object to a source-specific identifier for the object in a particular namespace, e.g. Satori, Facebook, Wikipedia, etc.</mso:type.object.description>
    <mso:type.object.name xml:lang="en">Subject Key</mso:type.object.name>
    <mso:type.object.type rdf:resource="http://knowledge.microsoft.com/mso/type.property" />
    <mso:type.property.expected_type rdf:resource="http://knowledge.microsoft.com/mso/type.key" />
    <mso:type.property.type rdf:resource="http://knowledge.microsoft.com/mso/type.object" />
  </rdf:Description>
  <rdf:Description rdf:about="http://knowledge.microsoft.com/mso/type.object.subtype">
    <mso:type.object.description xml:lang="en">Property relating an mso:type.object to its sub-types, sub-groupings that allow for more specificity in the description of instances. For example, the primary entity "fracture" would have as sub-types "wrist fracture" and "pathological fracture".</mso:type.object.description>
    <mso:type.object.name xml:lang="en">Subtype</mso:type.object.name>
    <mso:type.object.type rdf:resource="http://knowledge.microsoft.com/mso/type.property" />
    <mso:type.object.type rdf:resource="http://knowledge.microsoft.com/mso/type.virtual_property" />
    <mso:type.property.expected_type rdf:resource="http://knowledge.microsoft.com/mso/type.object" />
    <mso:type.property.inverse_of rdf:resource="mso:type.object.supertype" />
    <mso:type.property.type rdf:resource="http://knowledge.microsoft.com/mso/type.object" />
  </rdf:Description>
  <rdf:Description rdf:about="http://knowledge.microsoft.com/mso/type.object.supertype">
    <mso:type.object.description xml:lang="en">Property relating an mso:type.object to its supertypes. These are the more general grouping for the type. For example, the primary entity 'yellow corn' would have a super type of 'corn'. 'Wrist fracture' would have a super-type of 'fracture'.</mso:type.object.description>
    <mso:type.object.name xml:lang="en">Supertype</mso:type.object.name>
    <mso:type.object.type rdf:resource="http://knowledge.microsoft.com/mso/type.property" />
    <mso:type.object.type rdf:resource="http://knowledge.microsoft.com/mso/type.virtual_property" />
    <mso:type.property.expected_type rdf:resource="http://knowledge.microsoft.com/mso/type.object" />
    <mso:type.property.inverse_of rdf:resource="mso:type.object.subtype" />
    <mso:type.property.type rdf:resource="http://knowledge.microsoft.com/mso/type.object" />
  </rdf:Description>
  <rdf:Description rdf:about="http://knowledge.microsoft.com/mso/type.object.text">
    <mso:type.object.description xml:lang="en">A property that relates an object to information about a block of text that denotes the object.</mso:type.object.description>
    <mso:type.object.name xml:lang="en">Text</mso:type.object.name>
    <mso:type.object.type rdf:resource="http://knowledge.microsoft.com/mso/type.property" />
    <mso:type.property.expected_type rdf:resource="http://knowledge.microsoft.com/mso/common.text" />
    <mso:type.property.type rdf:resource="http://knowledge.microsoft.com/mso/type.object" />
  </rdf:Description>
  <rdf:Description rdf:about="http://knowledge.microsoft.com/mso/type.object.text_passage">
    <mso:type.object.description xml:lang="en">Property relating an mso:type.object to an mso:common.text value type that holds text regarding the entity. This property should be used when associating text passages that are not descriptions, in which case use type.object.description, or the text passages is not tokenized, in which case use type.object.tokenized_description.</mso:type.object.description>
    <mso:type.object.name xml:lang="en">Text Passage</mso:type.object.name>
    <mso:type.object.type rdf:resource="http://knowledge.microsoft.com/mso/type.property" />
    <mso:type.property.deprecation_info xml:lang="en">Use textPassage:type.object.textPassage instead. DeprecatedBy:[REDMOND\sunkumar] Successor:[textPassage:type.object.textPassage]</mso:type.property.deprecation_info>
    <mso:type.property.expected_type rdf:resource="http://knowledge.microsoft.com/mso/common.text" />
    <mso:type.property.type rdf:resource="http://knowledge.microsoft.com/mso/type.object" />
  </rdf:Description>
  <rdf:Description rdf:about="http://knowledge.microsoft.com/mso/type.object.tokenized_description">
    <mso:type.object.description xml:lang="en">A property that relates an entity to a tokenized description of the entity.  Note that this property should be used only when a description needs to be divided into tokens for some reason, e.g. to categorize phrases that make up the text.  Otherwise, the property type.object.description should be used.</mso:type.object.description>
    <mso:type.object.name xml:lang="en">Tokenized Description</mso:type.object.name>
    <mso:type.object.type rdf:resource="http://knowledge.microsoft.com/mso/type.property" />
    <mso:type.property.deprecation_info xml:lang="en">Use textPassage:type.object.tokenizedDescription instead. DeprecatedBy:[REDMOND\sunkumar] Successor:[textPassage:type.object.tokenizedDescription]</mso:type.property.deprecation_info>
    <mso:type.property.expected_type rdf:resource="http://knowledge.microsoft.com/mso/common.text" />
    <mso:type.property.type rdf:resource="http://knowledge.microsoft.com/mso/type.object" />
  </rdf:Description>
  <rdf:Description rdf:about="http://knowledge.microsoft.com/mso/type.object.triple">
    <mso:type.object.description xml:lang="en">A virtual property that relates an entity to a triple in which the entity appears as a subject.</mso:type.object.description>
    <mso:type.object.name xml:lang="en">Triple</mso:type.object.name>
    <mso:type.object.type rdf:resource="http://knowledge.microsoft.com/mso/type.property" />
    <mso:type.object.type rdf:resource="http://knowledge.microsoft.com/mso/type.virtual_property" />
    <mso:type.property.expected_type rdf:resource="http://knowledge.microsoft.com/mso/type.triple" />
    <mso:type.property.inverse_of rdf:resource="mso:type.triple.subject" />
    <mso:type.property.type rdf:resource="http://knowledge.microsoft.com/mso/type.object" />
  </rdf:Description>
  <rdf:Description rdf:about="http://knowledge.microsoft.com/mso/type.object.type">
    <mso:type.object.description xml:lang="en">A property that relates an object to one of its types, e.g. it relates the entity for Tom Hanks to the type mso:people.person.</mso:type.object.description>
    <mso:type.object.name xml:lang="en">Type</mso:type.object.name>
    <mso:type.object.type rdf:resource="http://knowledge.microsoft.com/mso/type.property" />
    <mso:type.property.expected_type rdf:resource="http://knowledge.microsoft.com/mso/type.type" />
    <mso:type.property.type rdf:resource="http://knowledge.microsoft.com/mso/type.object" />
  </rdf:Description>
  <rdf:Description rdf:about="http://knowledge.microsoft.com/mso/type.object.webpage">
    <mso:type.object.description xml:lang="en">A property that links an object to a related webpage.</mso:type.object.description>
    <mso:type.object.name xml:lang="en">Webpage</mso:type.object.name>
    <mso:type.object.type rdf:resource="http://knowledge.microsoft.com/mso/type.property" />
    <mso:type.property.expected_type rdf:resource="http://knowledge.microsoft.com/mso/common.webpage" />
    <mso:type.property.type rdf:resource="http://knowledge.microsoft.com/mso/type.object" />
  </rdf:Description>
  <rdf:Description rdf:about="http://knowledge.microsoft.com/mso/type.object.webpage_uri">
    <mso:type.object.description xml:lang="en">A property that links an object to the URL for a related webpage.  Note that this is a virtual property defined on the property common.webpage.uri.</mso:type.object.description>
    <mso:type.object.name xml:lang="en">Webpage</mso:type.object.name>
    <mso:type.object.type rdf:resource="http://knowledge.microsoft.com/mso/type.property" />
    <mso:type.object.type rdf:resource="http://knowledge.microsoft.com/mso/type.virtual_property" />
    <mso:type.property.expected_type rdf:resource="http://knowledge.microsoft.com/mso/type.uri" />
    <mso:type.property.type rdf:resource="http://knowledge.microsoft.com/mso/type.object" />
  </rdf:Description>
  <rdf:Description rdf:about="http://knowledge.microsoft.com/mso/type.property">
    <mso:type.object.description xml:lang="en">A relationship between two elements of the ontology, in most cases a relationship between an entity and another entity or a data value, e.g. type.object.name.</mso:type.object.description>
    <mso:type.object.name xml:lang="en">Property</mso:type.object.name>
    <mso:type.object.type rdf:resource="http://knowledge.microsoft.com/mso/type.type" />
    <mso:type.type.category rdf:resource="http://knowledge.microsoft.com/mso/type.category.metadata" />
    <mso:type.type.domain rdf:resource="http://knowledge.microsoft.com/mso/type" />
    <mso:type.type.includes rdf:resource="http://knowledge.microsoft.com/mso/type.object" />
  </rdf:Description>
  <rdf:Description rdf:about="http://knowledge.microsoft.com/mso/type.property.deprecation_info">
    <mso:type.object.description xml:lang="en">A property that links a deprecated property to information about when and why it was deprecated.</mso:type.object.description>
    <mso:type.object.name xml:lang="en">Deprecation Information</mso:type.object.name>
    <mso:type.object.type rdf:resource="http://knowledge.microsoft.com/mso/type.property" />
    <mso:type.property.expected_type rdf:resource="http://knowledge.microsoft.com/mso/type.text" />
    <mso:type.property.type rdf:resource="http://knowledge.microsoft.com/mso/type.property" />
  </rdf:Description>
  <rdf:Description rdf:about="http://knowledge.microsoft.com/mso/type.property.expected_type">
    <mso:type.object.description xml:lang="en">Also known as the range of a property, it is the type from which all of the values of the property are taken.</mso:type.object.description>
    <mso:type.object.name xml:lang="en">Expected Type</mso:type.object.name>
    <mso:type.object.type rdf:resource="http://knowledge.microsoft.com/mso/type.property" />
    <mso:type.property.expected_type rdf:resource="http://knowledge.microsoft.com/mso/type.type" />
    <mso:type.property.max_cardinality rdf:datatype="http://www.w3.org/2001/XMLSchema#int">1</mso:type.property.max_cardinality>
    <mso:type.property.type rdf:resource="http://knowledge.microsoft.com/mso/type.property" />
  </rdf:Description>
  <rdf:Description rdf:about="http://knowledge.microsoft.com/mso/type.property.inverse_of">
    <mso:type.object.description xml:lang="en">A property for properties that represents the inverse of the current property. For example, if Bob is the parent of Jill, then Jill is the child of Bob. Thus, mso:people.person.children would have a type.property.inverse_of property to mso:people.person.parent.</mso:type.object.description>
    <mso:type.object.name xml:lang="en">Inverse of</mso:type.object.name>
    <mso:type.object.type rdf:resource="http://knowledge.microsoft.com/mso/type.property" />
    <mso:type.property.expected_type rdf:resource="http://knowledge.microsoft.com/mso/type.property" />
    <mso:type.property.max_cardinality rdf:datatype="http://www.w3.org/2001/XMLSchema#int">1</mso:type.property.max_cardinality>
    <mso:type.property.type rdf:resource="http://knowledge.microsoft.com/mso/type.property" />
  </rdf:Description>
  <rdf:Description rdf:about="http://knowledge.microsoft.com/mso/type.property.max_cardinality">
    <mso:type.object.description xml:lang="en">The maximum number of values that a subject of the given property can be related to.</mso:type.object.description>
    <mso:type.object.name xml:lang="en">Maximum Cardinality</mso:type.object.name>
    <mso:type.object.type rdf:resource="http://knowledge.microsoft.com/mso/type.property" />
    <mso:type.property.expected_type rdf:resource="http://knowledge.microsoft.com/mso/type.decimal" />
    <mso:type.property.type rdf:resource="http://knowledge.microsoft.com/mso/type.property" />
  </rdf:Description>
  <rdf:Description rdf:about="http://knowledge.microsoft.com/mso/type.property.min_cardinality">
    <mso:type.object.description xml:lang="en">The minimum number of values that a subject of the given property can be related to.</mso:type.object.description>
    <mso:type.object.name xml:lang="en">Minimum Cardinality</mso:type.object.name>
    <mso:type.object.type rdf:resource="http://knowledge.microsoft.com/mso/type.property" />
    <mso:type.property.expected_type rdf:resource="http://knowledge.microsoft.com/mso/type.decimal" />
    <mso:type.property.type rdf:resource="http://knowledge.microsoft.com/mso/type.property" />
  </rdf:Description>
  <rdf:Description rdf:about="http://knowledge.microsoft.com/mso/type.property.precision">
    <mso:type.object.description xml:lang="en">A property that is used to relate a given property to an instance of type.unit specifying the accuracy or exactness of the property.  Among other things, the property type.property.precision is useful for determining when to conflate values of the given property.  For example, the type.property.unit of commerce.consumer_product.age is type.unit.month.  If we set type.property.precision for this same property to type.unit.month, it would mean that all measurements of product age that are in days, weeks, etc. can be rounded to the nearest month. </mso:type.object.description>
    <mso:type.object.name xml:lang="en">Precision of Property</mso:type.object.name>
    <mso:type.object.type rdf:resource="http://knowledge.microsoft.com/mso/type.property" />
    <mso:type.property.expected_type rdf:resource="http://knowledge.microsoft.com/mso/type.unit" />
    <mso:type.property.max_cardinality rdf:datatype="http://www.w3.org/2001/XMLSchema#int">1</mso:type.property.max_cardinality>
    <mso:type.property.type rdf:resource="http://knowledge.microsoft.com/mso/type.property" />
  </rdf:Description>
  <rdf:Description rdf:about="http://knowledge.microsoft.com/mso/type.property.subproperty">
    <mso:type.object.description xml:lang="en">Property relating an mso:type.property to another property of which the former is a subproperty. This means that for cases in which 'specific_property subproperty broad_property' is true, then for any instance x, for which 'x specific_property y', then 'x broad_property y' is also true. This allows us to express more specific relationship between types while still inferring a broader relationship.</mso:type.object.description>
    <mso:type.object.name xml:lang="en">Subproperty</mso:type.object.name>
    <mso:type.object.type rdf:resource="http://knowledge.microsoft.com/mso/type.property" />
    <mso:type.property.expected_type rdf:resource="http://knowledge.microsoft.com/mso/type.property" />
    <mso:type.property.type rdf:resource="http://knowledge.microsoft.com/mso/type.property" />
  </rdf:Description>
  <rdf:Description rdf:about="http://knowledge.microsoft.com/mso/type.property.type">
    <mso:type.object.description xml:lang="en">Also known as the domain of a property, it is the type on which a property is defined and to which all of the subjects of the property must belong.</mso:type.object.description>
    <mso:type.object.name xml:lang="en">Type</mso:type.object.name>
    <mso:type.object.type rdf:resource="http://knowledge.microsoft.com/mso/type.property" />
    <mso:type.property.expected_type rdf:resource="http://knowledge.microsoft.com/mso/type.type" />
    <mso:type.property.type rdf:resource="http://knowledge.microsoft.com/mso/type.property" />
  </rdf:Description>
  <rdf:Description rdf:about="http://knowledge.microsoft.com/mso/type.property.unit">
    <mso:type.object.description xml:lang="en">A unit of measure associated with the expected type of the property.  For example, type.property.unit is set to type.unit.miles_per_gallon on the property automotive.automotive_class.highway_fuel_economy to indicate the unit of measure for its values.</mso:type.object.description>
    <mso:type.object.name xml:lang="en">Unit</mso:type.object.name>
    <mso:type.object.type rdf:resource="http://knowledge.microsoft.com/mso/type.property" />
    <mso:type.property.expected_type rdf:resource="http://knowledge.microsoft.com/mso/type.unit" />
    <mso:type.property.type rdf:resource="http://knowledge.microsoft.com/mso/type.property" />
  </rdf:Description>
  <rdf:Description rdf:about="http://knowledge.microsoft.com/mso/type.publishable_object">
    <mso:type.object.description xml:lang="en">Type that is the collection of all Satori entities that should be published for consumption. This type allows for a general, high-level type that can be applied to any entity that needs publishing,  but which may not have other MSO types in the category of 'primary entity'. Note this type has the category 'abstract'; it receives special handling in the entity platform.</mso:type.object.description>
    <mso:type.object.name xml:lang="en">Publishable Object</mso:type.object.name>
    <mso:type.object.type rdf:resource="http://knowledge.microsoft.com/mso/type.type" />
    <mso:type.type.category rdf:resource="http://knowledge.microsoft.com/mso/type.category.abstract" />
    <mso:type.type.domain rdf:resource="http://knowledge.microsoft.com/mso/type" />
    <mso:type.type.includes rdf:resource="http://knowledge.microsoft.com/mso/type.object" />
  </rdf:Description>
  <rdf:Description rdf:about="http://knowledge.microsoft.com/mso/type.string">
    <mso:type.object.alias xml:lang="en">String</mso:type.object.alias>
    <mso:type.object.description xml:lang="en">A type containing any finite sequence of characters, i.e. letters, numerals, symbols and punctuation marks.  Although there is no distinction between mso:type.string and mso:type.text in the ontology, these two types of literals are handled differently at the implementation layer.  The type mso:type.string is language-independent, and the type mso:type.text is language-dependent.  Examples of strings in this sense include URIs, identification keys, and any set of characters that is the same in any language.</mso:type.object.description>
    <mso:type.object.name xml:lang="en">Machine Readable String</mso:type.object.name>
    <mso:type.object.type rdf:resource="http://knowledge.microsoft.com/mso/type.type" />
    <mso:type.type.category rdf:resource="http://knowledge.microsoft.com/mso/type.category.metadata" />
    <mso:type.type.domain rdf:resource="http://knowledge.microsoft.com/mso/type" />
    <mso:type.type.includes rdf:resource="http://knowledge.microsoft.com/mso/type.object" />
    <mso:type.type.includes rdf:resource="http://knowledge.microsoft.com/mso/type.value" />
  </rdf:Description>
  <rdf:Description rdf:about="http://knowledge.microsoft.com/mso/type.text">
    <mso:type.object.description xml:lang="en">A type containing any finite sequence of characters, i.e. letters, numerals, symbols and punctuation marks.  Although there is no distinction between mso:type.string and mso:type.text in the ontology, these two types of literals are handled differently at the implementation layer.  The type mso:type.string is language-independent, and the type mso:type.text is language-dependent.  Examples of text in this sense include any character string whose meaning may vary by language.</mso:type.object.description>
    <mso:type.object.name xml:lang="en">Text</mso:type.object.name>
    <mso:type.object.type rdf:resource="http://knowledge.microsoft.com/mso/type.type" />
    <mso:type.type.category rdf:resource="http://knowledge.microsoft.com/mso/type.category.metadata" />
    <mso:type.type.domain rdf:resource="http://knowledge.microsoft.com/mso/type" />
    <mso:type.type.includes rdf:resource="http://knowledge.microsoft.com/mso/type.object" />
    <mso:type.type.includes rdf:resource="http://knowledge.microsoft.com/mso/type.value" />
  </rdf:Description>
  <rdf:Description rdf:about="http://knowledge.microsoft.com/mso/type.triple">
    <mso:type.object.alias xml:lang="en">Assertion</mso:type.object.alias>
    <mso:type.object.alias xml:lang="en">Fact</mso:type.object.alias>
    <mso:type.object.alias xml:lang="en">Tuple</mso:type.object.alias>
    <mso:type.object.description xml:lang="en">A type containing instances of properties.  A triple consists of a subject (an entity, type or property), a property, and an object (an entity, type, property or literal), and it asserts that the subject is related to the object by the given property.  For example, the triples &lt;Paris, location.location.contained_by, France&gt; and &lt;Tale of Two Cities, book.written_work.author, Charles Dickens&gt; mean, respectively, that Paris is contained within France and Charles Dickens is the author of the work ???Tale of Two Cities???.</mso:type.object.description>
    <mso:type.object.name xml:lang="en">Triple</mso:type.object.name>
    <mso:type.object.type rdf:resource="http://knowledge.microsoft.com/mso/type.type" />
    <mso:type.type.category rdf:resource="http://knowledge.microsoft.com/mso/type.category.primary_entity" />
    <mso:type.type.domain rdf:resource="http://knowledge.microsoft.com/mso/type" />
    <mso:type.type.includes rdf:resource="http://knowledge.microsoft.com/mso/type.object" />
  </rdf:Description>
  <rdf:Description rdf:about="http://knowledge.microsoft.com/mso/type.triple.object">
    <mso:type.object.description xml:lang="en">A property that relates a triple to its object or final argument.  For example, France is the object of the triple &lt;Paris, location.location.contained_by, France&gt;.</mso:type.object.description>
    <mso:type.object.name xml:lang="en">Object</mso:type.object.name>
    <mso:type.object.type rdf:resource="http://knowledge.microsoft.com/mso/type.property" />
    <mso:type.property.expected_type rdf:resource="http://knowledge.microsoft.com/mso/type.object" />
    <mso:type.property.max_cardinality rdf:datatype="http://www.w3.org/2001/XMLSchema#int">1</mso:type.property.max_cardinality>
    <mso:type.property.type rdf:resource="http://knowledge.microsoft.com/mso/type.triple" />
  </rdf:Description>
  <rdf:Description rdf:about="http://knowledge.microsoft.com/mso/type.triple.property">
    <mso:type.object.description xml:lang="en">A property that relates a triple to the property that links the subject and object of the triple.  For example, location.location.contained_by is the property in the triple &lt;Paris, location.location.contained_by, France&gt;.</mso:type.object.description>
    <mso:type.object.name xml:lang="en">Property</mso:type.object.name>
    <mso:type.object.type rdf:resource="http://knowledge.microsoft.com/mso/type.property" />
    <mso:type.property.expected_type rdf:resource="http://knowledge.microsoft.com/mso/type.property" />
    <mso:type.property.max_cardinality rdf:datatype="http://www.w3.org/2001/XMLSchema#int">1</mso:type.property.max_cardinality>
    <mso:type.property.type rdf:resource="http://knowledge.microsoft.com/mso/type.triple" />
  </rdf:Description>
  <rdf:Description rdf:about="http://knowledge.microsoft.com/mso/type.triple.relation">
    <mso:type.object.description xml:lang="en">A property that specifies, in an informal way, the semantic relation between two entities in a triple.  Note that the property should be used only when there is no relevant property in the ontology or when the relevant property is not known.</mso:type.object.description>
    <mso:type.object.name xml:lang="en">Relation</mso:type.object.name>
    <mso:type.object.type rdf:resource="http://knowledge.microsoft.com/mso/type.property" />
    <mso:type.property.expected_type rdf:resource="http://knowledge.microsoft.com/mso/type.text" />
    <mso:type.property.max_cardinality rdf:datatype="http://www.w3.org/2001/XMLSchema#int">1</mso:type.property.max_cardinality>
    <mso:type.property.type rdf:resource="http://knowledge.microsoft.com/mso/type.triple" />
  </rdf:Description>
  <rdf:Description rdf:about="http://knowledge.microsoft.com/mso/type.triple.relaxed_object">
    <mso:type.object.description xml:lang="en">A property that relates a triple to its object or final argument, when the final argument is a nonstandard value, e.g. a blob of text rather than an entity. </mso:type.object.description>
    <mso:type.object.name xml:lang="en">Relaxed Object</mso:type.object.name>
    <mso:type.object.type rdf:resource="http://knowledge.microsoft.com/mso/type.property" />
    <mso:type.property.expected_type rdf:resource="http://knowledge.microsoft.com/mso/common.text" />
    <mso:type.property.max_cardinality rdf:datatype="http://www.w3.org/2001/XMLSchema#int">1</mso:type.property.max_cardinality>
    <mso:type.property.type rdf:resource="http://knowledge.microsoft.com/mso/type.triple" />
  </rdf:Description>
  <rdf:Description rdf:about="http://knowledge.microsoft.com/mso/type.triple.source">
    <mso:type.object.description xml:lang="en">A property that specifies the data source of the triple, e.g. Wikipedia, Freebase, IMDB, etc.</mso:type.object.description>
    <mso:type.object.name xml:lang="en">Source</mso:type.object.name>
    <mso:type.object.type rdf:resource="http://knowledge.microsoft.com/mso/type.property" />
    <mso:type.property.expected_type rdf:resource="http://knowledge.microsoft.com/mso/type.text" />
    <mso:type.property.type rdf:resource="http://knowledge.microsoft.com/mso/type.triple" />
  </rdf:Description>
  <rdf:Description rdf:about="http://knowledge.microsoft.com/mso/type.triple.subject">
    <mso:type.object.description xml:lang="en">A property that relates a triple to its subject or first argument.  For example, Paris is the subject of the triple &lt;Paris, location.location.contained_by, France&gt;.</mso:type.object.description>
    <mso:type.object.name xml:lang="en">Subject</mso:type.object.name>
    <mso:type.object.type rdf:resource="http://knowledge.microsoft.com/mso/type.property" />
    <mso:type.property.expected_type rdf:resource="http://knowledge.microsoft.com/mso/type.object" />
    <mso:type.property.max_cardinality rdf:datatype="http://www.w3.org/2001/XMLSchema#int">1</mso:type.property.max_cardinality>
    <mso:type.property.type rdf:resource="http://knowledge.microsoft.com/mso/type.triple" />
  </rdf:Description>
  <rdf:Description rdf:about="http://knowledge.microsoft.com/mso/type.triple.text">
    <mso:type.object.description xml:lang="en">A property that relates a triple to a text passage from which the triple was extracted.</mso:type.object.description>
    <mso:type.object.name xml:lang="en">Text</mso:type.object.name>
    <mso:type.object.type rdf:resource="http://knowledge.microsoft.com/mso/type.property" />
    <mso:type.property.expected_type rdf:resource="http://knowledge.microsoft.com/mso/type.text" />
    <mso:type.property.type rdf:resource="http://knowledge.microsoft.com/mso/type.triple" />
  </rdf:Description>
  <rdf:Description rdf:about="http://knowledge.microsoft.com/mso/type.type">
    <mso:type.object.description xml:lang="en">the type of which all other types are instances.</mso:type.object.description>
    <mso:type.object.name xml:lang="en">Type</mso:type.object.name>
    <mso:type.object.type rdf:resource="http://knowledge.microsoft.com/mso/type.type" />
    <mso:type.type.category rdf:resource="http://knowledge.microsoft.com/mso/type.category.metadata" />
    <mso:type.type.domain rdf:resource="http://knowledge.microsoft.com/mso/type" />
    <mso:type.type.includes rdf:resource="http://knowledge.microsoft.com/mso/type.object" />
  </rdf:Description>
  <rdf:Description rdf:about="http://knowledge.microsoft.com/mso/type.type.category">
    <mso:type.object.description xml:lang="en">A property that relates a type to the category of the type, e.g. primary entity, relationship, etc.</mso:type.object.description>
    <mso:type.object.name xml:lang="en">Category</mso:type.object.name>
    <mso:type.object.type rdf:resource="http://knowledge.microsoft.com/mso/type.property" />
    <mso:type.property.expected_type rdf:resource="http://knowledge.microsoft.com/mso/type.category" />
    <mso:type.property.max_cardinality rdf:datatype="http://www.w3.org/2001/XMLSchema#int">1</mso:type.property.max_cardinality>
    <mso:type.property.min_cardinality rdf:datatype="http://www.w3.org/2001/XMLSchema#int">1</mso:type.property.min_cardinality>
    <mso:type.property.type rdf:resource="http://knowledge.microsoft.com/mso/type.type" />
  </rdf:Description>
  <rdf:Description rdf:about="http://knowledge.microsoft.com/mso/type.type.deprecation_info">
    <mso:type.object.description xml:lang="en">A property that relates a type to information about why the type is deprecated and what the successor of the type is.</mso:type.object.description>
    <mso:type.object.name xml:lang="en">Deprecation Information</mso:type.object.name>
    <mso:type.object.type rdf:resource="http://knowledge.microsoft.com/mso/type.property" />
    <mso:type.property.expected_type rdf:resource="http://knowledge.microsoft.com/mso/type.text" />
    <mso:type.property.type rdf:resource="http://knowledge.microsoft.com/mso/type.type" />
  </rdf:Description>
  <rdf:Description rdf:about="http://knowledge.microsoft.com/mso/type.type.domain">
    <mso:type.object.description xml:lang="en">A property that relates a type to the domain of the type.</mso:type.object.description>
    <mso:type.object.name xml:lang="en">Domain</mso:type.object.name>
    <mso:type.object.type rdf:resource="http://knowledge.microsoft.com/mso/type.property" />
    <mso:type.property.expected_type rdf:resource="http://knowledge.microsoft.com/mso/type.domain" />
    <mso:type.property.max_cardinality rdf:datatype="http://www.w3.org/2001/XMLSchema#int">1</mso:type.property.max_cardinality>
    <mso:type.property.type rdf:resource="http://knowledge.microsoft.com/mso/type.type" />
  </rdf:Description>
  <rdf:Description rdf:about="http://knowledge.microsoft.com/mso/type.type.exclusive">
    <mso:type.object.description xml:lang="en">A property that relates two types when we want to stipulate that no entities are permitted to belong to both of the types, e.g. mso:time.event and mso:event.agent or mso:people.person and mso:organization.organization.  Note that this property should not be used in cases of "double identity", viz. cases where two distinct entities falling under two distinct concepts are referred to in the same way.  This happens often with organizations and the locations that they occupy.  For example, ???Stanford University??? is both a campus and an educational institution, but most people just refer to both entities with the same name.  Another case is compositions versus tracks or singles featuring the compositions, particularly in popular music.  These cases reflect a pervasive conceptual simplification that language users make, and it would be conterproductive to stipulate in the ontology that the types involved are exclusive.</mso:type.object.description>
    <mso:type.object.name xml:lang="en">Exclusive</mso:type.object.name>
    <mso:type.object.type rdf:resource="http://knowledge.microsoft.com/mso/type.property" />
    <mso:type.property.expected_type rdf:resource="http://knowledge.microsoft.com/mso/type.type" />
    <mso:type.property.type rdf:resource="http://knowledge.microsoft.com/mso/type.type" />
  </rdf:Description>
  <rdf:Description rdf:about="http://knowledge.microsoft.com/mso/type.type.exhaustive">
    <mso:type.object.description xml:lang="en">A property that relates a type to a subtype of the given type, when it is not possible for an entity to belong to the given type without also belonging to one of the subtypes specified by a mso:type.type.exhaustive assertion.  For example, mso:sports.sports_agent has two subtypes:  mso:sports.team and mso:sports.athlete.  Since these two subtypes are related to mso:sports.agent via mso:type.type.exhaustive, every entity in mso:sports.agent is also in either mso:sports.team or mso:sports.athlete.</mso:type.object.description>
    <mso:type.object.name xml:lang="en">Exhaustive</mso:type.object.name>
    <mso:type.object.type rdf:resource="http://knowledge.microsoft.com/mso/type.property" />
    <mso:type.property.expected_type rdf:resource="http://knowledge.microsoft.com/mso/type.type" />
    <mso:type.property.type rdf:resource="http://knowledge.microsoft.com/mso/type.type" />
  </rdf:Description>
  <rdf:Description rdf:about="http://knowledge.microsoft.com/mso/type.type.includes">
    <mso:type.object.description xml:lang="en">A property that relates a type to a base class of the type, i.e. it relates a type to another type from which it inherits properties.  Note, however, that inclusion is not enforced and has no meaning with respect the instances in the entity graph.</mso:type.object.description>
    <mso:type.object.name xml:lang="en">Includes</mso:type.object.name>
    <mso:type.object.type rdf:resource="http://knowledge.microsoft.com/mso/type.property" />
    <mso:type.property.expected_type rdf:resource="http://knowledge.microsoft.com/mso/type.type" />
    <mso:type.property.type rdf:resource="http://knowledge.microsoft.com/mso/type.type" />
  </rdf:Description>
  <rdf:Description rdf:about="http://knowledge.microsoft.com/mso/type.unit">
    <mso:type.object.description xml:lang="en">A precisely defined division of a physical quantity that is used as a standard for measurement of the same physical quantity.</mso:type.object.description>
    <mso:type.object.name xml:lang="en">Unit</mso:type.object.name>
    <mso:type.object.type rdf:resource="http://knowledge.microsoft.com/mso/type.type" />
    <mso:type.type.category rdf:resource="http://knowledge.microsoft.com/mso/type.category.enumeration" />
    <mso:type.type.domain rdf:resource="http://knowledge.microsoft.com/mso/type" />
    <mso:type.type.includes rdf:resource="http://knowledge.microsoft.com/mso/type.object" />
  </rdf:Description>
  <rdf:Description rdf:about="http://knowledge.microsoft.com/mso/type.uri">
    <mso:type.object.description xml:lang="en">The type for literals that reference an Internet resource.</mso:type.object.description>
    <mso:type.object.name xml:lang="en">URI</mso:type.object.name>
    <mso:type.object.type rdf:resource="http://knowledge.microsoft.com/mso/type.type" />
    <mso:type.type.category rdf:resource="http://knowledge.microsoft.com/mso/type.category.metadata" />
    <mso:type.type.domain rdf:resource="http://knowledge.microsoft.com/mso/type" />
    <mso:type.type.includes rdf:resource="http://knowledge.microsoft.com/mso/type.object" />
    <mso:type.type.includes rdf:resource="http://knowledge.microsoft.com/mso/type.value" />
  </rdf:Description>
  <rdf:Description rdf:about="http://knowledge.microsoft.com/mso/type.value">
    <mso:type.object.description xml:lang="en">The type that is the base class for all of the literals, e.g. Boolean, datetime, decimal, string, text, uri.</mso:type.object.description>
    <mso:type.object.name xml:lang="en">Value</mso:type.object.name>
    <mso:type.object.type rdf:resource="http://knowledge.microsoft.com/mso/type.type" />
    <mso:type.type.category rdf:resource="http://knowledge.microsoft.com/mso/type.category.metadata" />
    <mso:type.type.domain rdf:resource="http://knowledge.microsoft.com/mso/type" />
    <mso:type.type.includes rdf:resource="http://knowledge.microsoft.com/mso/type.object" />
  </rdf:Description>
  <rdf:Description rdf:about="http://knowledge.microsoft.com/mso/type.virtual_property">
    <mso:type.object.description xml:lang="en">A property that is defined in terms of other properties.  In many cases it will be either an inverse of a given property or the transitive closure of a set of properties.</mso:type.object.description>
    <mso:type.object.name xml:lang="en">Virtual Property</mso:type.object.name>
    <mso:type.object.type rdf:resource="http://knowledge.microsoft.com/mso/type.type" />
    <mso:type.type.category rdf:resource="http://knowledge.microsoft.com/mso/type.category.metadata" />
    <mso:type.type.domain rdf:resource="http://knowledge.microsoft.com/mso/type" />
    <mso:type.type.includes rdf:resource="http://knowledge.microsoft.com/mso/type.object" />
  </rdf:Description>
</rdf:RDF>